Workbook
Name Treasury_5Yr: #REF!

Sheet Summary
B2: Prepared By: Tadeusz Godlewski
B4: ASML HOLDING N.V.
B7: Valuation Date: | D7: 46161 | F7: Market Price: | H7: 1249.8 | J7: DCF Fair Value: | L7: ='DCF Model'!D76 -> 724.28577
B11: Implied Downside: | D11: =('DCF Model'!D76-H7)/H7 -> -0.42047866 | F11: Premium to Fair Value: | H11: =(H7-'DCF Model'!D76)/'DCF Model'!D76 -> 0.725562 | J11: Conclusion: | L11: Overvalued
B16: WACC: | D16: =WACC!E36 -> 0.085549212 | F16: Terminal Growth: | H16: ='Growth (g)'!E23 -> 0.030483507 | J16: Forecast Period: | L16: 2026-2035
B20: Enterprise Value (Mln): | F20: ='DCF Model'!D69 -> 270629.12 | H20: Equity Value (Mln): | K20: ='DCF Model'!D72 -> 279154.22
B24: ASML Holding N.V. was valued using a driver-based FCFF DCF model. The model estimates fair value at €724.29 per share, compared with a market price of €1,249.80 as of 19 May 2026, implying 42.05% downside and a 72.56% premium to fair value. ASML is a high-quality business with a strong competitive position, supported by EUV dominance, AI-related demand, and long-term growth potential. However, the current market price already reflects a significant premium for these strengths. Under the model’s assumptions, ASML appears overvalued with limited margin of safety. A multiples valuation was used as a supporting cross-check but excluded from the final fair value estimate due to ASML’s limited comparability with listed semiconductor equipment peers.

Sheet Final Valuation
C3: Final Valuation
L8: Valuation Methodology: Although a multiples valuation was conducted as a supporting cross-check, it was not incorporated into the final fair value estimate due to ASML’s limited direct comparability with peers. ASML’s dominant position in EUV lithography, unique market structure, and strategic importance make peer-based multiples less reliable. Therefore, the final valuation is based primarily on the DCF approach
D9: DCF Valuation | F9: ='DCF Model'!D76 -> 724.28577
H10: =F9 -> 724.28577 | I10: per share
D14: Multiples Valuation | F14: ='Multiples Valuation '!C47 -> 1190.5385
C19: Current Market Price: 1,249.80 EUR (as of May 19th 2026)
C23: Result: ASML Holding NV Appears Overvalued

Sheet DCF Model
C3: FCFF | D3: Forecast Period | O3: Dutch Tax | Q3: Delta Revenue
C4: Year | D4: 2026 E | E4: 2027 E | F4: 2028 E | G4: 2029 E | H4: 2030 E | I4: 2031 E | J4: 2032 E | K4: 2033 E | L4: 2034 E | M4: 2035 E | O4: 0.258
C5: Revenue | D5: =('ASML Revenue Model'!G7)*(1+$Q$4) -> 40676.557 | E5: =('ASML Revenue Model'!H7)*(1+$Q$4) -> 47267.583 | F5: =('ASML Revenue Model'!I7)*(1+$Q$4) -> 53461.654 | G5: =('ASML Revenue Model'!J7)*(1+$Q$4) -> 59100.617 | H5: =('ASML Revenue Model'!K7)*(1+$Q$4) -> 65320.659 | I5: =('ASML Revenue Model'!L7)*(1+$Q$4) -> 70804.677 | J5: =('ASML Revenue Model'!M7)*(1+$Q$4) -> 75637.401 | K5: =('ASML Revenue Model'!N7)*(1+$Q$4) -> 80264.155 | ... M5: =('ASML Revenue Model'!P7)*(1+$Q$4) -> 89086.048
B6: - | C6: Operating Expenses | D6: =('Cost Analysis'!G12+'Cost Analysis'!G16+'Cost Analysis'!G20)*(1+$Q$7) -> 25554.213 | E6: =('Cost Analysis'!H12+'Cost Analysis'!H16+'Cost Analysis'!H20)*(1+$Q$7) -> 29553.087 | F6: =('Cost Analysis'!I12+'Cost Analysis'!I16+'Cost Analysis'!I20)*(1+$Q$7) -> 33265.418 | G6: =('Cost Analysis'!J12+'Cost Analysis'!J16+'Cost Analysis'!J20)*(1+$Q$7) -> 36596.845 | H6: =('Cost Analysis'!K12+'Cost Analysis'!K16+'Cost Analysis'!K20)*(1+$Q$7) -> 40252.517 | I6: =('Cost Analysis'!L12+'Cost Analysis'!L16+'Cost Analysis'!L20)*(1+$Q$7) -> 43419.516 | J6: =('Cost Analysis'!M12+'Cost Analysis'!M16+'Cost Analysis'!M20)*(1+$Q$7) -> 46156.173 | K6: =('Cost Analysis'!N12+'Cost Analysis'!N16+'Cost Analysis'!N20)*(1+$Q$7) -> 48738.762 | ... M6: =('Cost Analysis'!P12+'Cost Analysis'!P16+'Cost Analysis'!P20)*(1+$Q$7) -> 53561.16 | O6: WACC | Q6: Delta Operating Expenses
B7: = | C7: Operating Profit (EBIT) | D7: =D5-D6 -> 15122.344 | E7: =E5-E6 -> 17714.496 | F7: =F5-F6 -> 20196.236 | G7: =G5-G6 -> 22503.772 | H7: =H5-H6 -> 25068.142 | I7: =I5-I6 -> 27385.161 | J7: =J5-J6 -> 29481.228 | K7: =K5-K6 -> 31525.392 | ... M7: =M5-M6 -> 35524.888 | O7: =WACC!E36*(1+$O$10) -> 0.085549212
B8: - | C8: Income Tax | D8: =D7*$O$4 -> 3901.5648 | E8: =E7*$O$4 -> 4570.3399 | F8: =F7*$O$4 -> 5210.6289 | G8: =G7*$O$4 -> 5805.9731 | H8: =H7*$O$4 -> 6467.5807 | I8: =I7*$O$4 -> 7065.3714 | J8: =J7*$O$4 -> 7606.1568 | K8: =K7*$O$4 -> 8133.5513 | ... M8: =M7*$O$4 -> 9165.4212
B9: = | C9: Net Operating Profit After Tax (NOPAT) | D9: =D7-D8 -> 11220.779 | E9: =E7-E8 -> 13144.156 | F9: =F7-F8 -> 14985.607 | G9: =G7-G8 -> 16697.799 | H9: =H7-H8 -> 18600.562 | I9: =I7-I8 -> 20319.789 | J9: =J7-J8 -> 21875.071 | K9: =K7-K8 -> 23391.841 | ... M9: =M7-M8 -> 26359.467 | O9: Delta WACC
B10: + | C10: Depreciation and Amortisation | D10: ='Cost Analysis'!G32 -> 1140.5818 | E10: ='Cost Analysis'!H32 -> 1325.3959 | F10: ='Cost Analysis'!I32 -> 1499.0794 | G10: ='Cost Analysis'!J32 -> 1657.1974 | H10: ='Cost Analysis'!K32 -> 1831.6091 | I10: ='Cost Analysis'!L32 -> 1985.3824 | J10: ='Cost Analysis'!M32 -> 2120.8934 | K10: ='Cost Analysis'!N32 -> 2250.6288 | ... M10: ='Cost Analysis'!P32 -> 2497.9971
B11: - | C11: Capital Expenditure | D11: ='Pro Forma Financial Statement'!C34 -> 2644.684 | E11: ='Pro Forma Financial Statement'!D34 -> 3073.2153 | F11: ='Pro Forma Financial Statement'!E34 -> 3475.9378 | G11: ='Pro Forma Financial Statement'!F34 -> 3842.5685 | H11: ='Pro Forma Financial Statement'!G34 -> 4246.9795 | I11: ='Pro Forma Financial Statement'!H34 -> 4603.536 | J11: ='Pro Forma Financial Statement'!I34 -> 4917.7472 | K11: ='Pro Forma Financial Statement'!J34 -> 5218.5667 | ... M11: ='Pro Forma Financial Statement'!L34 -> 5792.1433
B12: - | C12: Investment in Net Working Capital | D12: ='Pro Forma Financial Statement'!C29 -> 4889.1998 | E12: ='Pro Forma Financial Statement'!D29 -> 1732.2026 | F12: ='Pro Forma Financial Statement'!E29 -> 1627.8782 | G12: ='Pro Forma Financial Statement'!F29 -> 1481.9889 | H12: ='Pro Forma Financial Statement'!G29 -> 1634.7037 | I12: ='Pro Forma Financial Statement'!H29 -> 1441.2673 | J12: ='Pro Forma Financial Statement'!I29 -> 1270.0994 | K12: ='Pro Forma Financial Statement'!J29 -> 1215.9678 | ... M12: ='Pro Forma Financial Statement'!L29 -> 1135.6669
B13: = | C13: FCFF (Free Cash Flow to the Firm) | D13: =D9+D10-D11-D12 -> 4827.4774 | E13: =E9+E10-E11-E12 -> 9664.1339 | F13: =F9+F10-F11-F12 -> 11380.871 | G13: =G9+G10-G11-G12 -> 13030.439 | H13: =H9+H10-H11-H12 -> 14550.488 | I13: =I9+I10-I11-I12 -> 16260.368 | J13: =J9+J10-J11-J12 -> 17808.118 | K13: =K9+K10-K11-K12 -> 19207.936 | ... M13: =M9+M10-M11-M12 -> 21929.654
C15: Method: Direct Method, uses method
C16: Year | D16: 2026 E | E16: 2027 E | F16: 2028 E | G16: 2029 E | H16: 2030 E | I16: 2031 E | J16: 2032 E | K16: 2033 E | L16: 2034 E | M16: 2035 E
C17: Finance Costs | D17: =-'Pro Forma Financial Statement'!C38 -> 118.3 | E17: =-'Pro Forma Financial Statement'!D38 -> 118.3 | F17: =-'Pro Forma Financial Statement'!E38 -> 118.3 | G17: =-'Pro Forma Financial Statement'!F38 -> 118.3 | H17: =-'Pro Forma Financial Statement'!G38 -> 118.3 | I17: =-'Pro Forma Financial Statement'!H38 -> 118.3 | J17: =-'Pro Forma Financial Statement'!I38 -> 118.3 | K17: =-'Pro Forma Financial Statement'!J38 -> 118.3 | ... M17: =-'Pro Forma Financial Statement'!L38 -> 118.3
B18: - | C18: Tax Shield (Finance Costs) | D18: =D17*$O$4 -> 30.5214 | E18: =E17*$O$4 -> 30.5214 | F18: =F17*$O$4 -> 30.5214 | G18: =G17*$O$4 -> 30.5214 | H18: =H17*$O$4 -> 30.5214 | I18: =I17*$O$4 -> 30.5214 | J18: =J17*$O$4 -> 30.5214 | K18: =K17*$O$4 -> 30.5214 | ... M18: =M17*$O$4 -> 30.5214
B19: + | C19: Debt Repayments (+) / Debt Drawdowns (–)
B20: = | C20: Cash Flows to Creditors (Adjusted for Tax Shield) | D20: =D17-D18 -> 87.7786 | E20: =E17-E18 -> 87.7786 | F20: =F17-F18 -> 87.7786 | G20: =G17-G18 -> 87.7786 | H20: =H17-H18 -> 87.7786 | I20: =I17-I18 -> 87.7786 | J20: =J17-J18 -> 87.7786 | K20: =K17-K18 -> 87.7786 | ... M20: =M17-M18 -> 87.7786
B21: - | C21: Capital Contributions
B22: + | C22: Dividends Paid and Share Buybacks | D22: =('Pro Forma Financial Statement'!C39+'Pro Forma Financial Statement'!C40)*-1 -> 7582.2464 | E22: =('Pro Forma Financial Statement'!D39+'Pro Forma Financial Statement'!D40)*-1 -> 8892.182 | F22: =('Pro Forma Financial Statement'!E39+'Pro Forma Financial Statement'!E40)*-1 -> 10146.322 | G22: =('Pro Forma Financial Statement'!F39+'Pro Forma Financial Statement'!F40)*-1 -> 11312.428 | H22: =('Pro Forma Financial Statement'!G39+'Pro Forma Financial Statement'!G40)*-1 -> 12608.324 | I22: =('Pro Forma Financial Statement'!H39+'Pro Forma Financial Statement'!H40)*-1 -> 13779.222 | J22: =('Pro Forma Financial Statement'!I39+'Pro Forma Financial Statement'!I40)*-1 -> 14838.463 | K22: =('Pro Forma Financial Statement'!J39+'Pro Forma Financial Statement'!J40)*-1 -> 15871.475 | ... M22: =('Pro Forma Financial Statement'!L39+'Pro Forma Financial Statement'!L40)*-1 -> 17892.608
B23: + | C23: Total Cash Flows for the Year | D23: ='Pro Forma Financial Statement'!C44 -> -2842.5476 | E23: ='Pro Forma Financial Statement'!D44 -> 684.17325 | F23: ='Pro Forma Financial Statement'!E44 -> 1146.7703 | G23: ='Pro Forma Financial Statement'!F44 -> 1630.2326 | H23: ='Pro Forma Financial Statement'!G44 -> 1854.3849 | I23: ='Pro Forma Financial Statement'!H44 -> 2393.3678 | J23: ='Pro Forma Financial Statement'!I44 -> 2881.8764 | K23: ='Pro Forma Financial Statement'!J44 -> 3248.6819 | ... M23: ='Pro Forma Financial Statement'!L44 -> 3949.2678
B24: = | C24: Cash Flows to Equity (FCFE) | D24: =D21+D22+D23 -> 4739.6988 | E24: =E21+E22+E23 -> 9576.3553 | F24: =F21+F22+F23 -> 11293.092 | G24: =G21+G22+G23 -> 12942.66 | H24: =H21+H22+H23 -> 14462.709 | I24: =I21+I22+I23 -> 16172.59 | J24: =J21+J22+J23 -> 17720.339 | K24: =K21+K22+K23 -> 19120.157 | ... M24: =M21+M22+M23 -> 21841.875
B25: = | C25: FCFF (Free Cash Flow to the Firm) | D25: =D24+D20 -> 4827.4774 | E25: =E24+E20 -> 9664.1339 | F25: =F24+F20 -> 11380.871 | G25: =G24+G20 -> 13030.439 | H25: =H24+H20 -> 14550.488 | I25: =I24+I20 -> 16260.368 | J25: =J24+J20 -> 17808.118 | K25: =K24+K20 -> 19207.936 | ... M25: =M24+M20 -> 21929.654
C27: Check | D27: =D13-D25 -> 0 | E27: =E13-E25 -> 0 | F27: =F13-F25 -> 0 | G27: =G13-G25 -> 0 | H27: =H13-H25 -> 0 | I27: =I13-I25 -> 0 | J27: =J13-J25 -> 0 | K27: =K13-K25 -> 0 | ... M27: =M13-M25 -> 0
C30: FCFE | D30: Forecast Period
C31: Year | D31: 2026 E | E31: 2027 E | F31: 2028 E | G31: 2029 E | H31: 2030 E | I31: 2031 E | J31: 2032 E | K31: 2033 E | L31: 2034 E | M31: 2035 E
C32: Revenue | D32: =D5 -> 40676.557 | E32: =E5 -> 47267.583 | F32: =F5 -> 53461.654 | G32: =G5 -> 59100.617 | H32: =H5 -> 65320.659 | I32: =I5 -> 70804.677 | J32: =J5 -> 75637.401 | K32: =K5 -> 80264.155 | ... M32: =M5 -> 89086.048
B33: - | C33: Operating Expenses | D33: =D6 -> 25554.213 | E33: =E6 -> 29553.087 | F33: =F6 -> 33265.418 | G33: =G6 -> 36596.845 | H33: =H6 -> 40252.517 | I33: =I6 -> 43419.516 | J33: =J6 -> 46156.173 | K33: =K6 -> 48738.762 | ... M33: =M6 -> 53561.16
B34: = | C34: Operating Profit (EBIT) | D34: =D32-D33 -> 15122.344 | E34: =E32-E33 -> 17714.496 | F34: =F32-F33 -> 20196.236 | G34: =G32-G33 -> 22503.772 | H34: =H32-H33 -> 25068.142 | I34: =I32-I33 -> 27385.161 | J34: =J32-J33 -> 29481.228 | K34: =K32-K33 -> 31525.392 | ... M34: =M32-M33 -> 35524.888
B35: - | C35: Finance Costs | D35: =D17 -> 118.3 | E35: =E17 -> 118.3 | F35: =F17 -> 118.3 | G35: =G17 -> 118.3 | H35: =H17 -> 118.3 | I35: =I17 -> 118.3 | J35: =J17 -> 118.3 | K35: =K17 -> 118.3 | ... M35: =M17 -> 118.3
B36: = | C36: Profit Before Tax | D36: =D34-D35 -> 15004.044 | E36: =E34-E35 -> 17596.196 | F36: =F34-F35 -> 20077.936 | G36: =G34-G35 -> 22385.472 | H36: =H34-H35 -> 24949.842 | I36: =I34-I35 -> 27266.861 | J36: =J34-J35 -> 29362.928 | K36: =K34-K35 -> 31407.092 | ... M36: =M34-M35 -> 35406.588
B37: - | C37: Income Tax | D37: =D36*$O$4 -> 3871.0434 | E37: =E36*$O$4 -> 4539.8185 | F37: =F36*$O$4 -> 5180.1075 | G37: =G36*$O$4 -> 5775.4517 | H37: =H36*$O$4 -> 6437.0593 | I37: =I36*$O$4 -> 7034.85 | J37: =J36*$O$4 -> 7575.6354 | K37: =K36*$O$4 -> 8103.0299 | ... M37: =M36*$O$4 -> 9134.8998
B38: = | C38: Net Profit | D38: =D36-D37 -> 11133.001 | E38: =E36-E37 -> 13056.377 | F38: =F36-F37 -> 14897.829 | G38: =G36-G37 -> 16610.02 | H38: =H36-H37 -> 18512.783 | I38: =I36-I37 -> 20232.011 | J38: =J36-J37 -> 21787.293 | K38: =K36-K37 -> 23304.063 | ... M38: =M36-M37 -> 26271.689
B39: + | C39: Debt Repayments (–) / Debt Drawdowns (+)
B40: + | C40: Depreciation and Amortisation | D40: =D10 -> 1140.5818 | E40: =E10 -> 1325.3959 | F40: =F10 -> 1499.0794 | G40: =G10 -> 1657.1974 | H40: =H10 -> 1831.6091 | I40: =I10 -> 1985.3824 | J40: =J10 -> 2120.8934 | K40: =K10 -> 2250.6288 | ... M40: =M10 -> 2497.9971
B41: - | C41: Capital Expenditure | D41: =D11 -> 2644.684 | E41: =E11 -> 3073.2153 | F41: =F11 -> 3475.9378 | G41: =G11 -> 3842.5685 | H41: =H11 -> 4246.9795 | I41: =I11 -> 4603.536 | J41: =J11 -> 4917.7472 | K41: =K11 -> 5218.5667 | ... M41: =M11 -> 5792.1433
B42: - | C42: Investment in Net Working Capital | D42: =D12 -> 4889.1998 | E42: =E12 -> 1732.2026 | F42: =F12 -> 1627.8782 | G42: =G12 -> 1481.9889 | H42: =H12 -> 1634.7037 | I42: =I12 -> 1441.2673 | J42: =J12 -> 1270.0994 | K42: =K12 -> 1215.9678 | ... M42: =M12 -> 1135.6669
B43: = | C43: FCFE (Free Cash Flow to Equity) | D43: =D38+D39+D40-D41-D42 -> 4739.6988 | E43: =E38+E39+E40-E41-E42 -> 9576.3553 | F43: =F38+F39+F40-F41-F42 -> 11293.092 | G43: =G38+G39+G40-G41-G42 -> 12942.66 | H43: =H38+H39+H40-H41-H42 -> 14462.709 | I43: =I38+I39+I40-I41-I42 -> 16172.59 | J43: =J38+J39+J40-J41-J42 -> 17720.339 | K43: =K38+K39+K40-K41-K42 -> 19120.157 | ... M43: =M38+M39+M40-M41-M42 -> 21841.875
C45: Metoda: uses
C46: Year | D46: 2026 E | E46: 2027 E | F46: 2028 E | G46: 2029 E | H46: 2030 E | I46: 2031 E | J46: 2032 E | K46: 2033 E | L46: 2034 E | M46: 2035 E
B47: - | C47: Capital Contributions
B48: + | C48: Dividends Paid | D48: =D22 -> 7582.2464 | E48: =E22 -> 8892.182 | F48: =F22 -> 10146.322 | G48: =G22 -> 11312.428 | H48: =H22 -> 12608.324 | I48: =I22 -> 13779.222 | J48: =J22 -> 14838.463 | K48: =K22 -> 15871.475 | ... M48: =M22 -> 17892.608
B49: + | C49: Total Cash Flows for the Year | D49: =D23 -> -2842.5476 | E49: =E23 -> 684.17325 | F49: =F23 -> 1146.7703 | G49: =G23 -> 1630.2326 | H49: =H23 -> 1854.3849 | I49: =I23 -> 2393.3678 | J49: =J23 -> 2881.8764 | K49: =K23 -> 3248.6819 | ... M49: =M23 -> 3949.2678
B50: = | C50: Cash Flows to Equity | D50: =-D47+D48+D49 -> 4739.6988 | E50: =-E47+E48+E49 -> 9576.3553 | F50: =-F47+F48+F49 -> 11293.092 | G50: =-G47+G48+G49 -> 12942.66 | H50: =-H47+H48+H49 -> 14462.709 | I50: =-I47+I48+I49 -> 16172.59 | J50: =-J47+J48+J49 -> 17720.339 | K50: =-K47+K48+K49 -> 19120.157 | ... M50: =-M47+M48+M49 -> 21841.875
C52: Check | D52: =D43-D50 -> 0 | E52: =E43-E50 -> 0 | F52: =F43-F50 -> 0 | G52: =G43-G50 -> 0 | H52: =H43-H50 -> 0 | I52: =I43-I50 -> 0 | J52: =J43-J50 -> 0 | K52: =K43-K50 -> 0 | ... M52: =M43-M50 -> 0
D55: 2026 E | E55: 2027 E | F55: 2028 E | G55: 2029 E | H55: 2030 E | I55: 2031 E | J55: 2032 E | K55: 2033 E | L55: 2034 E | M55: 2035 E
C56: WACC | D56: =$O$7 -> 0.085549212 | E56: =$O$7 -> 0.085549212 | F56: =$O$7 -> 0.085549212 | G56: =$O$7 -> 0.085549212 | H56: =$O$7 -> 0.085549212 | I56: =$O$7 -> 0.085549212 | J56: =$O$7 -> 0.085549212 | K56: =$O$7 -> 0.085549212 | ... M56: =$O$7 -> 0.085549212
C57: Time until cash flows | D57: 1 | E57: 2 | F57: 3 | G57: 4 | H57: 5 | I57: 6 | J57: 7 | K57: 8 | L57: 9 | M57: 10
C59: Discount denominator | D59: =1+D57*D56 -> 1.0855492 | E59: =D59*(1+E56) -> 1.1784171 | F59: =E59*(1+F56) -> 1.2792297 | G59: =F59*(1+G56) -> 1.3886668 | H59: =G59*(1+H56) -> 1.5074662 | I59: =H59*(1+I56) -> 1.6364287 | J59: =I59*(1+J56) -> 1.7764239 | K59: =J59*(1+K56) -> 1.9283956 | L59: =K59*(1+L56) -> 2.0933683 | M59: =L59*(1+M56) -> 2.2724543
O60: Delta g
C61: Residual growth rate (g) | M61: =3.05%*(1+O61) -> 0.0305
C62: Residual value | M62: =M13*(1+M61)/(M56-M61) -> 410514.66
C64: FCFF+RV | D64: =D13+D62 -> 4827.4774 | E64: =E13+E62 -> 9664.1339 | F64: =F13+F62 -> 11380.871 | G64: =G13+G62 -> 13030.439 | H64: =H13+H62 -> 14550.488 | I64: =I13+I62 -> 16260.368 | J64: =J13+J62 -> 17808.118 | K64: =K13+K62 -> 19207.936 | ... M64: =M13+M62 -> 432444.32
C66: Discounted FCFF | D66: =D64/D59 -> 4447.0369 | E66: =E64/E59 -> 8200.9451 | F66: =F64/F59 -> 8896.6588 | G66: =G64/G59 -> 9383.4161 | H66: =H64/H59 -> 9652.2812 | I66: =I64/I59 -> 9936.4964 | J66: =J64/J59 -> 10024.701 | K66: =K64/K59 -> 9960.5784 | ... M66: =M64/M59 -> 190298.35
C69: Enterprise Value (EV) | D69: =SUM(D66:M66) -> 270629.12 | E69: mln | H69: Sensitivity Analysis of Estimated Share Value to Changes in WACC and Growth Rate
C70: Excess Cash | D70: ='Balance Sheet'!E24 -> 12916 | E70: mln
C71: Interest Bearing Debt | D71: ='Balance Sheet'!E45+'Balance Sheet'!E59 -> 4390.9 | E71: mln | H71: Change in Growth Rate (g)
C72: Equity | D72: =D69+D70-D71 -> 279154.22 | E72: mln | G72: Change in WACC | H72: =D76 -> 724.28577 | I72: -0.15 | J72: -0.1 | K72: -0.05 | L72: 0 | M72: 0.05 | N72: 0.1 | O72: 0.15
H73: 0.15 | I73: 555.35368 | J73: 562.60923 | K73: 570.18362 | L73: 578.09834 | M73: 586.37685 | N73: 595.04482 | O73: 604.1304
C74: Number of Shares outstanding | D74: 385.42 | E74: mln | H74: 0.1 | I74: 593.44354 | J74: 601.94241 | K74: 610.83927 | L74: 620.16277 | M74: 629.94434 | N74: 640.21859 | O74: 651.0237
H75: 0.05 | I75: 636.75024 | J75: 646.78752 | K75: 657.32788 | L75: 668.41014 | M75: 680.07716 | N75: 692.3765 | O75: 705.36098
C76: Value per share | D76: =D72/D74 -> 724.28577 | H76: 0 | I76: 686.4006 | J76: 698.36604 | K76: 710.97656 | L76: 724.28577 | M76: 738.35338 | N76: 753.24612 | O76: 769.03879
H77: -0.05 | I77: 743.86999 | J77: 758.28794 | K77: 773.54677 | L77: 789.72224 | M77: 806.8995 | N77: 825.1746 | O77: 844.65625
H78: -0.1 | I78: 811.12825 | J78: 828.71936 | K78: 847.42779 | L78: 867.36349 | M78: 888.6513 | N78: 911.43363 | O78: 935.87357
H79: -0.15 | I79: 890.86573 | J79: 912.64541 | K79: 935.94372 | L79: 960.92525 | M79: 987.77923 | N79: 1016.7244 | O79: 1048.0149
H83: Sensitivity Analysis of Estimated Share Value to Changes in Revenue and Operating Expenses
H85: Change in Revenue
G86: Change in Operating Expenses | H86: =D76 -> 724.28577 | I86: -0.15 | J86: -0.1 | K86: -0.05 | L86: 0 | M86: 0.05 | N86: 0.1 | O86: 0.15
H87: 0.15 | I87: 192.64738 | J87: 302.9872 | K87: 413.32701 | L87: 523.66682 | M87: 634.00663 | N87: 744.34644 | O87: 854.68625
H88: 0.1 | I88: 259.52037 | J88: 369.86018 | K88: 480.19999 | L88: 590.5398 | M88: 700.87961 | N88: 811.21942 | O88: 921.55923
H89: 0.05 | I89: 326.39335 | J89: 436.73316 | K89: 547.07297 | L89: 657.41278 | M89: 767.75259 | N89: 878.09241 | O89: 988.43222
H90: 0 | I90: 393.26634 | J90: 503.60615 | K90: 613.94596 | L90: 724.28577 | M90: 834.62558 | N90: 944.96539 | O90: 1055.3052
H91: -0.05 | I91: 460.13932 | J91: 570.47913 | K91: 680.81894 | L91: 791.15875 | M91: 901.49856 | N91: 1011.8384 | O91: 1122.1782
H92: -0.1 | I92: 527.0123 | J92: 637.35211 | K92: 747.69192 | L92: 858.03173 | M92: 968.37155 | N92: 1078.7114 | O92: 1189.0512
H93: -0.15 | I93: 593.88529 | J93: 704.2251 | K93: 814.56491 | L93: 924.90472 | M93: 1035.2445 | N93: 1145.5843 | O93: 1255.9242

Sheet Growth (g)
C7: End Year | E7: 2030
C8: Reinvestment Rate
C9: NOPAT | E9: ='DCF Model'!H9 -> 18600.562
C10: Capital Expenditure (Capex) | E10: ='Cash Flow'!J79 -> 4246.9795
C11: Depreciation and Amortisation | E11: ='Cost Analysis'!K32 -> 1831.6091
C12: Net Investment in Non-current Assets | E12: =E10-E11 -> 2415.3703
C13: Investment in Net Working Capital | E13: ='Pro Forma Financial Statement'!G29 -> 1634.7037
C14: Total Investment Expenditure | E14: =E12+E13 -> 4050.074
K15: 2015 | L15: 2025
C16: Reinvestment rate | E16: =(E10-E11+E13)/E9 -> 0.21773934 | J16: Invested Capital | K16: 8162.089 | L16: ='Balance Sheet'!E45+'Balance Sheet'!E43+'Balance Sheet'!E59-'Balance Sheet'!E24 -> 15659.9 | N16: =(L16-K16)/(L17-K17) -> 0.99132893
J17: NOPAT | K17: 1380.6743 | L17: ='Statement of Profit or Loss'!F22 -> 8944.068
C18: ROIC | E18: 0.2655
C19: WACC | E19: ='DCF Model'!O7 -> 0.085549212
C21: RONIC | E21: 0.14
C23: g | E23: =E21*E16 -> 0.030483507

Sheet Multiples Valuation 
B4: Multiples-Based Valuation: ASML
B5: Comparable Companies
B6: In milions
B7: Companies | C7: Equity Value (100%) | D7: EV | E7: EBITDA TTM | F7: Net Income TTM | G7: EV/EBITDA | H7: P/E | I7: original currency | J7: EBC exchange rate | K7: 46161
B8: Applied Materials, Inc. (AMAT) | C8: =328210 -> 328210 | D8: =326430 -> 326430 | E8: =11147 -> 11147 | F8: =8508 -> 8508 | G8: =D8/E8 -> 29.284112 | H8: =C8/F8 -> 38.576634 | I8: USD | J8: EUR / US dollar | K8: 1.162
B9: Lam Research Corporation (LRCX) | C9: =367730 -> 367730 | D9: =366710 -> 366710 | E9: =8072.097 -> 8072.097 | F9: =6708.202 -> 6708.202 | G9: =D9/E9 -> 45.429335 | H9: =C9/F9 -> 54.817968 | I9: USD | J9: EUR / JPY | K9: 184.89
B10: Tokyo Electron Limited (8035.T) | C10: =23860000 -> 23860000 | D10: =23350000 -> 23350000 | E10: =706282 -> 706282 | F10: =574454 -> 574454 | G10: =D10/E10 -> 33.060449 | H10: =C10/F10 -> 41.535092 | I10: JPY
B11: KLA Corporation (KLAC) | C11: =244170 -> 244170 | D11: =245360 -> 245360 | E11: =6061.254 -> 6061.254 | F11: =4670.561 -> 4670.561 | G11: =D11/E11 -> 40.480072 | H11: =C11/F11 -> 52.278516 | I11: USD
B12: Onto Innovation Inc. (ONTO) | C12: =13520 -> 13520 | D12: =12900 -> 12900 | E12: =225.54 -> 225.54 | F12: =106.414 -> 106.414 | G12: =D12/E12 -> 57.196063 | H12: =C12/F12 -> 127.05095 | I12: USD | J12: *not included
B14: Mean | G14: =AVERAGE(G8:G11) -> 37.063492 | H14: =AVERAGE(H8:H11) -> 46.802053
B15: Median | G15: =MEDIAN(G8:G11) -> 36.770261 | H15: =MEDIAN(H8:H11) -> 46.906804
B19: Target Company Data - ASML
B20: EBITDA | C20: 11944.3 | D20: EUR m
B21: Net Income | C21: 10011.1 | D21: EUR m
B23: Debt | C23: 4390.9 | D23: EUR m
B24: Cash | C24: 13321.9 | D24: EUR m
B26: Shares Outstanding (millions) | C26: 385.42 | D26: m shares
B29: Valuation Results
C30: EV/EBITDA | D30: P/E
B31: Median Multiple | C31: =G15 -> 36.770261 | D31: =H15 -> 46.906804
B32: Valuation Base (EUR m) | C32: =C20 -> 11944.3 | D32: =C21 -> 10011.1
B33: Implied Value (EUR m ) | C33: =C31*C32 -> 439195.02 | D33: =D31*D32 -> 469588.71
B34: Value Type | C34: EV | D34: Equity
B36: Bridge to Equity Value:
B37: Implied Value | C37: =C33 -> 439195.02 | D37: =D33 -> 469588.71
B38: Less: Debt | C38: =C23 -> 4390.9
B39: Plus: Cash | C39: =C24 -> 13321.9
B40: Equity Value (EUR m ) | C40: =C37-C38+C39 -> 448126.02 | D40: =D33 -> 469588.71
B41: Price per Share (EUR m) | C41: =C40/$C$26 -> 1162.6953 | D41: =D40/$C$26 -> 1218.3818
B43: Weights | C43: 0.5 | D43: 0.5
C45: EUR | D45: USD
B46: Weighted Average Equity Value | C46: =SUMPRODUCT(C40:D40,C43:D43) -> 458857.37 | D46: =C46*K8 -> 533192.26
B47: Weighted Average Price per Share | C47: =SUMPRODUCT(C41:D41,C43:D43) -> 1190.5385 | D47: =C47*K8 -> 1383.4058

Sheet ASML Revenue Model
B1: EUR million
B2: Revenue | C2: Historical Period | G2: Forecast Period | R2: Delta Revenue
C3: 2022 | D3: 2023 | E3: 2024 | F3: 2025 | G3: 2026 E | H3: 2027 E | I3: 2028 E | J3: 2029 E | K3: 2030 E | L3: 2031 E | M3: 2032 E | N3: 2033 E | O3: 2034 E | P3: 2035 E
B4: Net System Sales | C4: 15430.3 | D4: 21938.6 | E4: 21768.7 | F4: 24474.3 | G4: =G29 -> 31005.739 | H4: =H29 -> 35996.145 | I4: =I29 -> 40643.588 | J4: =J29 -> 44598.92 | K4: =K29 -> 48986.257 | L4: =L29 -> 52666.395 | M4: =M29 -> 55577.013 | N4: =N29 -> 58156.458 | ... P4: =P29 -> 62514.449
B5: Net Service and field option sales | C5: 5743.1 | D5: 5619.9 | E5: 6494.2 | F5: 8193 | G5: =G66*G67 -> 9669.8187 | H5: =H66*H67 -> 11270.438 | I5: =I66*I67 -> 12817.066 | J5: =J66*J67 -> 14500.698 | K5: =K66*K67 -> 16333.403 | L5: =L66*L67 -> 18137.282 | M5: =M66*M67 -> 20059.388 | N5: =N66*N67 -> 22106.697 | ... P5: =P66*P67 -> 26570.6
B6: Ratio of revenue source | C6: =C5/C4 -> 0.37219626 | D6: =D5/D4 -> 0.25616493 | E6: =E5/E4 -> 0.29832742 | F6: =F5/F4 -> 0.33475932 | G6: =G5/G4 -> 0.3118719 | H6: =H5/H4 -> 0.31310126 | I6: =I5/I4 -> 0.31535272 | J6: =J5/J4 -> 0.32513562 | ... P6: =P5/P4 -> 0.42503133 | R6: CAGR
B7: Total Net Sales | C7: =C5+C4 -> 21173.4 | D7: =D5+D4 -> 27558.5 | E7: =E5+E4 -> 28262.9 | F7: =F5+F4 -> 32667.3 | G7: =(G4+G5)+(1+$R$3) -> 40676.557 | H7: =(H4+H5)+(1+$R$3) -> 47267.583 | I7: =(I4+I5)+(1+$R$3) -> 53461.654 | J7: =(J4+J5)+(1+$R$3) -> 59100.617 | K7: =(K4+K5)+(1+$R$3) -> 65320.659 | L7: =(L4+L5)+(1+$R$3) -> 70804.677 | M7: =(M4+M5)+(1+$R$3) -> 75637.401 | N7: =(N4+N5)+(1+$R$3) -> 80264.155 | ... P7: =(P4+P5)+(1+$R$3) -> 89086.048 | R7: =(P7/F7)^(1/10)-1 -> 0.10552774
B10: System Sales (units) | C10: 2022 | D10: 2023 | E10: 2024 | F10: 2025 | G10: 2026 E | H10: 2027 E | I10: 2028 E | J10: 2029 E | K10: 2030 E | L10: 2031 E | M10: 2032 E | N10: 2033 E | O10: 2034 E | P10: 2035 E
B11: EXE | C11: 0 | D11: 0 | E11: 2 | F11: 4 | G11: =ROUND(F11*(1+G45),0) -> 8 | H11: =ROUND(G11*(1+H45),0) -> 12 | I11: =ROUND(H11*(1+I45),0) -> 18 | J11: =ROUND(I11*(1+J45),0) -> 23 | K11: =ROUND(J11*(1+K45),0) -> 29 | L11: =ROUND(K11*(1+L45),0) -> 33 | M11: =ROUND(L11*(1+M45),0) -> 36 | N11: =ROUND(M11*(1+N45),0) -> 39 | ... P11: =ROUND(O11*(1+P45),0) -> 45
B12: NXE | C12: 40 | D12: 53 | E12: 42 | F12: 44 | G12: =ROUND(F12*(1+G46),0) -> 57 | H12: =ROUND(G12*(1+H46),0) -> 63 | I12: =ROUND(H12*(1+I46),0) -> 66 | J12: =ROUND(I12*(1+J46),0) -> 68 | K12: =ROUND(J12*(1+K46),0) -> 70 | L12: =ROUND(K12*(1+L46),0) -> 72 | M12: =ROUND(L12*(1+M46),0) -> 73 | N12: =ROUND(M12*(1+N46),0) -> 73 | ... P12: =ROUND(O12*(1+P46),0) -> 71
B13: ArF immersion | C13: 81 | D13: 125 | E13: 129 | F13: 131 | G13: =ROUND(F13*(1+G47),0) -> 135 | H13: =ROUND(G13*(1+H47),0) -> 138 | I13: =ROUND(H13*(1+I47),0) -> 139 | J13: =ROUND(I13*(1+J47),0) -> 139 | K13: =ROUND(J13*(1+K47),0) -> 138 | L13: =ROUND(K13*(1+L47),0) -> 137 | M13: =ROUND(L13*(1+M47),0) -> 136 | N13: =ROUND(M13*(1+N47),0) -> 135 | ... P13: =ROUND(O13*(1+P47),0) -> 131
B14: ArF dry | C14: 28 | D14: 32 | E14: 28 | F14: 16 | G14: =ROUND(F14*(1+G48),0) -> 24 | H14: =ROUND(G14*(1+H48),0) -> 26 | I14: =ROUND(H14*(1+I48),0) -> 27 | J14: =ROUND(I14*(1+J48),0) -> 28 | K14: =ROUND(J14*(1+K48),0) -> 29 | L14: =ROUND(K14*(1+L48),0) -> 29 | M14: =ROUND(L14*(1+M48),0) -> 29 | N14: =ROUND(M14*(1+N48),0) -> 29 | ... P14: =ROUND(O14*(1+P48),0) -> 29
B15: KrF | C15: 151 | D15: 184 | E15: 152 | F15: 78 | G15: =ROUND(F15*(1+G49),0) -> 98 | H15: =ROUND(G15*(1+H49),0) -> 108 | I15: =ROUND(H15*(1+I49),0) -> 110 | J15: =ROUND(I15*(1+J49),0) -> 110 | K15: =ROUND(J15*(1+K49),0) -> 110 | L15: =ROUND(K15*(1+L49),0) -> 110 | M15: =ROUND(L15*(1+M49),0) -> 110 | N15: =ROUND(M15*(1+N49),0) -> 110 | ... P15: =ROUND(O15*(1+P49),0) -> 110
B16: I-line | C16: 45 | D16: 55 | E16: 65 | F16: 54 | G16: =ROUND(F16*(1+G50),0) -> 54 | H16: =ROUND(G16*(1+H50),0) -> 54 | I16: =ROUND(H16*(1+I50),0) -> 53 | J16: =ROUND(I16*(1+J50),0) -> 52 | K16: =ROUND(J16*(1+K50),0) -> 51 | L16: =ROUND(K16*(1+L50),0) -> 50 | M16: =ROUND(L16*(1+M50),0) -> 49 | N16: =ROUND(M16*(1+N50),0) -> 48 | ... P16: =ROUND(O16*(1+P50),0) -> 46
B17: Metrology & Inspection | C17: 216 | D17: 151 | E17: 165 | F17: 208 | G17: =ROUND(F17*(1+G51),0) -> 250 | H17: =ROUND(G17*(1+H51),0) -> 275 | I17: =ROUND(H17*(1+I51),0) -> 297 | J17: =ROUND(I17*(1+J51),0) -> 321 | K17: =ROUND(J17*(1+K51),0) -> 347 | L17: =ROUND(K17*(1+L51),0) -> 371 | M17: =ROUND(L17*(1+M51),0) -> 397 | N17: =ROUND(M17*(1+N51),0) -> 425 | ... P17: =ROUND(O17*(1+P51),0) -> 474
B18: Net System Sales (units) | C18: =SUM(C11:C17) -> 561 | D18: =SUM(D11:D17) -> 600 | E18: =SUM(E11:E17) -> 583 | F18: 535 | G18: =SUM(G11:G17) -> 626 | H18: =SUM(H11:H17) -> 676 | I18: =SUM(I11:I17) -> 710 | J18: =SUM(J11:J17) -> 741 | K18: =SUM(K11:K17) -> 774 | L18: =SUM(L11:L17) -> 802 | M18: =SUM(M11:M17) -> 830 | N18: =SUM(N11:N17) -> 859 | ... P18: =SUM(P11:P17) -> 906
B21: System Sales (Revenue) | C21: 2022 | D21: 2023 | E21: 2024 | F21: 2025 | G21: 2026 E | H21: 2027 E | I21: 2028 E | J21: 2029 E | K21: 2030 E | L21: 2031 E | M21: 2032 E | N21: 2033 E | O21: 2034 E | P21: 2035 E
B22: EXE | C22: 0 | D22: 0 | E22: 465 | F22: 1156.9 | G22: =G11*G33 -> 2545.18 | H22: =H11*H33 -> 4199.547 | I22: =I11*I33 -> 6740.2729 | J22: =J11*J33 -> 9043.1995 | K22: =K11*K33 -> 11972.41 | L22: =L11*L33 -> 14168.728 | M22: =M11*M33 -> 16075.066 | N22: =N11*N33 -> 17937.094 | ... P22: =P11*P33 -> 21743.897
B23: NXE | C23: 7045.3 | D23: 9124 | E23: 7856.4 | F23: 10445.8 | G23: =G12*G34 -> 14479.303 | H23: =H12*H34 -> 17123.681 | I23: =I12*I34 -> 18836.049 | J23: =J12*J34 -> 20183.112 | K23: =K12*K34 -> 21400.035 | L23: =L12*L34 -> 22671.809 | M23: =M12*M34 -> 23446.429 | N23: =N12*N34 -> 23915.357 | ... P23: =P12*P34 -> 24199.852
B24: ArF immersion | C24: 5236.5 | D24: 9017.4 | E24: 9667 | F24: 10311.4 | G24: =G13*G35 -> 10732.514 | H24: =H13*H35 -> 11080.725 | I24: =I13*I35 -> 11272.63 | J24: =J13*J35 -> 11385.357 | K24: =K13*K35 -> 11416.482 | L24: =L13*L35 -> 11447.091 | M24: =M13*M35 -> 11477.171 | N24: =N13*N35 -> 11506.708 | ... P24: =P13*P35 -> 11390.201
B25: ArF dry | C25: 623.7 | D25: 780.2 | E25: 774.4 | F25: 427 | G25: =G14*G36 -> 646.905 | H25: =H14*H36 -> 707.82189 | I25: =I14*I36 -> 742.39626 | J25: =J14*J36 -> 777.59135 | K25: =K14*K36 -> 813.41609 | L25: =L14*L36 -> 821.55025 | M25: =M14*M36 -> 829.76575 | N25: =N14*N36 -> 838.06341 | ... P25: =P14*P36 -> 854.90849
B26: KrF | C26: 1653.7 | D26: 2202.5 | E26: 1991.2 | F26: 1001.3 | G26: =G15*G37 -> 1270.624 | H26: =H15*H37 -> 1414.2823 | I26: =I15*I37 -> 1454.8775 | J26: =J15*J37 -> 1469.4262 | K26: =K15*K37 -> 1484.1205 | L26: =L15*L37 -> 1498.9617 | M26: =M15*M37 -> 1513.9513 | N26: =N15*N37 -> 1529.0908 | ... P26: =P15*P37 -> 1559.8256
B27: I-line | C27: 211.5 | D27: 278.4 | E27: 369.2 | F27: 307.3 | G27: =G16*G38 -> 310.373 | H27: =H16*H38 -> 313.47673 | I27: =I16*I38 -> 310.74832 | J27: =J16*J38 -> 307.934 | K27: =K16*K38 -> 305.03231 | L27: =L16*L38 -> 302.0418 | M27: =M16*M38 -> 298.96097 | N27: =N16*N38 -> 295.78833 | ... P27: =P16*P38 -> 289.16143
B28: Metrology & Inspection | C28: 659.6 | D28: 536.1 | E28: 645.5 | F28: 824.6 | G28: =G17*G39 -> 1020.8389 | H28: =H17*H39 -> 1156.6105 | I28: =I17*I39 -> 1286.6135 | J28: =J17*J39 -> 1432.2998 | K28: =K17*K39 -> 1594.761 | L28: =L17*L39 -> 1756.2133 | M28: =M17*M39 -> 1935.6689 | N28: =N17*N39 -> 2134.3553 | ... P28: =P17*P39 -> 2476.6035
B29: Net System Sales | C29: =SUM(C22:C28) -> 15430.3 | D29: =SUM(D22:D28) -> 21938.6 | E29: =SUM(E22:E28) -> 21768.7 | F29: =SUM(F22:F28) -> 24474.3 | G29: =SUM(G22:G28) -> 31005.739 | H29: =SUM(H22:H28) -> 35996.145 | I29: =SUM(I22:I28) -> 40643.588 | J29: =SUM(J22:J28) -> 44598.92 | ... P29: =SUM(P22:P28) -> 62514.449
B32: System Sales (Price per unit) | C32: 2022 | D32: 2023 | E32: 2024 | F32: 2025 | G32: 2026 E | H32: 2027 E | I32: 2028 E | J32: 2029 E | K32: 2030 E | L32: 2031 E | M32: 2032 E | N32: 2033 E | O32: 2034 E | P32: 2035 E
B33: EXE | C33: 0 | D33: 0 | E33: =E22/E11 -> 232.5 | F33: =F22/F11 -> 289.225 | G33: =F33*(1+G54) -> 318.1475 | H33: =G33*(1+H54) -> 349.96225 | I33: =H33*(1+I54) -> 374.45961 | J33: =I33*(1+J54) -> 393.18259 | K33: =J33*(1+K54) -> 412.84172 | L33: =K33*(1+L54) -> 429.35539 | M33: =L33*(1+M54) -> 446.5296 | N33: =M33*(1+N54) -> 459.92549 | ... P33: =O33*(1+P54) -> 483.19772
B34: NXE | C34: =C23/C12 -> 176.1325 | D34: =D23/D12 -> 172.15094 | E34: =E23/E12 -> 187.05714 | F34: =F23/F12 -> 237.40455 | G34: =F34*(1+G55) -> 254.02286 | H34: =G34*(1+H55) -> 271.80446 | I34: =H34*(1+I55) -> 285.39469 | J34: =I34*(1+J55) -> 296.81047 | K34: =J34*(1+K55) -> 305.71479 | L34: =K34*(1+L55) -> 314.88623 | M34: =L34*(1+M55) -> 321.18396 | N34: =M34*(1+N55) -> 327.60764 | ... P34: =O34*(1+P55) -> 340.84299
B35: ArF immersion | C35: =C24/C13 -> 64.648148 | D35: =D24/D13 -> 72.1392 | E35: =E24/E13 -> 74.937984 | F35: =F24/F13 -> 78.712977 | G35: =F35*(1+G56) -> 79.500107 | H35: =G35*(1+H56) -> 80.295108 | I35: =H35*(1+I56) -> 81.098059 | J35: =I35*(1+J56) -> 81.90904 | K35: =J35*(1+K56) -> 82.72813 | L35: =K35*(1+L56) -> 83.555411 | M35: =L35*(1+M56) -> 84.390965 | N35: =M35*(1+N56) -> 85.234875 | ... P35: =O35*(1+P56) -> 86.948096
B36: ArF dry | C36: =C25/C14 -> 22.275 | D36: =D25/D14 -> 24.38125 | E36: =E25/E14 -> 27.657143 | F36: =F25/F14 -> 26.6875 | G36: =F36*(1+G56) -> 26.954375 | H36: =G36*(1+H56) -> 27.223919 | I36: =H36*(1+I56) -> 27.496158 | J36: =I36*(1+J56) -> 27.77112 | K36: =J36*(1+K56) -> 28.048831 | L36: =K36*(1+L56) -> 28.329319 | M36: =L36*(1+M56) -> 28.612612 | N36: =M36*(1+N56) -> 28.898738 | ... P36: =O36*(1+P56) -> 29.479603
B37: KrF | C37: =C26/C15 -> 10.951656 | D37: =D26/D15 -> 11.970109 | E37: =E26/E15 -> 13.1 | F37: =F26/F15 -> 12.837179 | G37: =F37*(1+G56) -> 12.965551 | H37: =G37*(1+H56) -> 13.095207 | I37: =H37*(1+I56) -> 13.226159 | J37: =I37*(1+J56) -> 13.35842 | K37: =J37*(1+K56) -> 13.492005 | L37: =K37*(1+L56) -> 13.626925 | M37: =L37*(1+M56) -> 13.763194 | N37: =M37*(1+N56) -> 13.900826 | ... P37: =O37*(1+P56) -> 14.180232
B38: I-line | C38: =C27/C16 -> 4.7 | D38: =D27/D16 -> 5.0618182 | E38: =E27/E16 -> 5.68 | F38: =F27/F16 -> 5.6907407 | G38: =F38*(1+G56) -> 5.7476481 | H38: =G38*(1+H56) -> 5.8051246 | I38: =H38*(1+I56) -> 5.8631759 | J38: =I38*(1+J56) -> 5.9218076 | K38: =J38*(1+K56) -> 5.9810257 | L38: =K38*(1+L56) -> 6.040836 | M38: =L38*(1+M56) -> 6.1012443 | N38: =M38*(1+N56) -> 6.1622568 | ... P38: =O38*(1+P56) -> 6.2861181
B39: Metrology & Inspection | C39: =C28/C17 -> 3.0537037 | D39: =D28/D17 -> 3.5503311 | E39: =E28/E17 -> 3.9121212 | F39: =F28/F17 -> 3.9644231 | G39: =F39*(1+G57) -> 4.0833558 | H39: =G39*(1+H57) -> 4.2058564 | I39: =H39*(1+I57) -> 4.3320321 | J39: =I39*(1+J57) -> 4.4619931 | K39: =J39*(1+K57) -> 4.5958529 | L39: =K39*(1+L57) -> 4.7337285 | M39: =L39*(1+M57) -> 4.8757403 | N39: =M39*(1+N57) -> 5.0220125 | ... P39: =O39*(1+P57) -> 5.2249019
B40: Average Price Per Unit | C40: =C29/C18 -> 27.504991 | D40: =D29/D18 -> 36.564333 | E40: =E29/E18 -> 37.339108 | F40: =F29/F18 -> 45.746355 | G40: =G29/G18 -> 49.529934 | H40: =H29/H18 -> 53.248735 | I40: =I29/I18 -> 57.24449 | J40: =J29/J18 -> 60.187476 | ... P40: =P29/P18 -> 69.000495
F43: FORECAST ASSUMPTIONS | G43: 2026 E | H43: 2027 E | I43: 2028 E | J43: 2029 E | K43: 2030 E | L43: 2031 E | M43: 2032 E | N43: 2033 E | O43: 2034 E | P43: 2035 E
F44: YoY (%) Unit Growth
F45: EXE (High-NA EUV) | G45: 1 | H45: 0.5 | I45: 0.5 | J45: 0.3 | K45: 0.25 | L45: 0.15 | M45: 0.1 | N45: 0.08 | O45: 0.08 | P45: 0.08
F46: NXE (EUV) | G46: 0.3 | H46: 0.1 | I46: 0.04 | J46: 0.03 | K46: 0.03 | L46: 0.03 | M46: 0.02 | N46: 0 | O46: -0.01 | P46: -0.02
F47: ArF immersion | G47: 0.03 | H47: 0.02 | I47: 0.01 | J47: 0 | K47: -0.01 | L47: -0.01 | M47: -0.01 | N47: -0.01 | O47: -0.01 | P47: -0.02
F48: ArF dry | G48: 0.5 | H48: 0.1 | I48: 0.05 | J48: 0.05 | K48: 0.05 | L48: 0 | M48: 0 | N48: 0 | O48: 0 | P48: 0
F49: KrF | G49: 0.25 | H49: 0.1 | I49: 0.02 | J49: 0 | K49: 0 | L49: 0 | M49: 0 | N49: 0 | O49: 0 | P49: 0
F50: I-line | G50: 0 | H50: 0 | I50: -0.01 | J50: -0.01 | K50: -0.01 | L50: -0.02 | M50: -0.02 | N50: -0.02 | O50: -0.02 | P50: -0.03
F51: Metrology & Inspection | G51: 0.2 | H51: 0.1 | I51: 0.08 | J51: 0.08 | K51: 0.08 | L51: 0.07 | M51: 0.07 | N51: 0.07 | O51: 0.06 | P51: 0.05
F53: YoY (%) Price Growth
F54: EXE | G54: 0.1 | H54: 0.1 | I54: 0.07 | J54: 0.05 | K54: 0.05 | L54: 0.04 | M54: 0.04 | N54: 0.03 | O54: 0.03 | P54: 0.02
F55: NXE | G55: 0.07 | H55: 0.07 | I55: 0.05 | J55: 0.04 | K55: 0.03 | L55: 0.03 | M55: 0.02 | N55: 0.02 | O55: 0.02 | P55: 0.02
F56: DUV (ArF imm/dry, KrF, i-line) | G56: 0.01 | H56: 0.01 | I56: 0.01 | J56: 0.01 | K56: 0.01 | L56: 0.01 | M56: 0.01 | N56: 0.01 | O56: 0.01 | P56: 0.01
F57: Metrology & Inspection | G57: 0.03 | H57: 0.03 | I57: 0.03 | J57: 0.03 | K57: 0.03 | L57: 0.03 | M57: 0.03 | N57: 0.03 | O57: 0.02 | P57: 0.02
F59: Service Revenue Driver
F60: Revenue per installed unit (EUR m) | G60: =G67 -> 1.5738637 | H60: =H67 -> 1.6525569 | I60: =I67 -> 1.7021336 | J60: =J67 -> 1.7531976 | K60: =K67 -> 1.8057935 | L60: =L67 -> 1.8419094 | M60: =M67 -> 1.8787476 | N60: =N67 -> 1.9163226 | ... P60: =P67 -> 1.993742
F61: Growth in rev/installed unit | G61: 0.06 | H61: 0.05 | I61: 0.03 | J61: 0.03 | K61: 0.03 | L61: 0.02 | M61: 0.02 | N61: 0.02 | O61: 0.02 | P61: 0.02
B64: Cumulative units sold (installed base proxy, from 2015) | C64: 2022 | D64: 2023 | E64: 2024 | F64: 2025 | G64: 2026 E | H64: 2027 E | I64: 2028 E | J64: 2029 E | K64: 2030 E | L64: 2031 E | M64: 2032 E | N64: 2033 E | O64: 2034 E | P64: 2035 E
B65: Units sold in year | C65: =C18 -> 561 | D65: =D18 -> 600 | E65: =E18 -> 583 | F65: =F18 -> 535 | G65: =G18 -> 626 | H65: =H18 -> 676 | I65: =I18 -> 710 | J65: =J18 -> 741 | ... P65: =P18 -> 906
B66: Cumulative installed base | C66: 3800 | D66: =C66+D65 -> 4400 | E66: =D66+E65 -> 4983 | F66: =E66+F65 -> 5518 | G66: =F66+G65 -> 6144 | H66: =G66+H65 -> 6820 | I66: =H66+I65 -> 7530 | J66: =I66+J65 -> 8271 | K66: =J66+K65 -> 9045 | ... P66: =O66+P65 -> 13327
B67: Service rev per installed unit (EUR m) | C67: =C5/C66 -> 1.5113421 | D67: =D5/D66 -> 1.27725 | E67: =E5/E66 -> 1.3032711 | F67: =F5/F66 -> 1.4847771 | G67: =F67*(1+G61) -> 1.5738637 | H67: =G67*(1+H61) -> 1.6525569 | I67: =H67*(1+I61) -> 1.7021336 | J67: =I67*(1+J61) -> 1.7531976 | K67: =J67*(1+K61) -> 1.8057935 | L67: =K67*(1+L61) -> 1.8419094 | M67: =L67*(1+M61) -> 1.8787476 | N67: =M67*(1+N61) -> 1.9163226 | ... P67: =O67*(1+P61) -> 1.993742

Sheet Pro Forma Financial Statement
B5: Statement of Profit or Loss | C5: Forecast Period
C6: 2026 E | D6: 2027 E | E6: 2028 E | F6: 2029 E | G6: 2030 E | H6: 2031 E | I6: 2032 E | J6: 2033 E | K6: 2034 E | L6: 2035 E | N6: Dutch Tax
B7: Revenue | C7: ='ASML Revenue Model'!G7 -> 40676.557 | D7: ='ASML Revenue Model'!H7 -> 47267.583 | E7: ='ASML Revenue Model'!I7 -> 53461.654 | F7: ='ASML Revenue Model'!J7 -> 59100.617 | G7: ='ASML Revenue Model'!K7 -> 65320.659 | H7: ='ASML Revenue Model'!L7 -> 70804.677 | I7: ='ASML Revenue Model'!M7 -> 75637.401 | J7: ='ASML Revenue Model'!N7 -> 80264.155 | ... L7: ='ASML Revenue Model'!P7 -> 89086.048 | N7: 0.258
A8: - | B8: Cost of Sales | C8: ='Cost Analysis'!G12 -> 19512.621 | D8: ='Cost Analysis'!H12 -> 22579.813 | E8: ='Cost Analysis'!I12 -> 25431.81 | F8: ='Cost Analysis'!J12 -> 27996.074 | G8: ='Cost Analysis'!K12 -> 30811.878 | H8: ='Cost Analysis'!L12 -> 33257.09 | I8: ='Cost Analysis'!M12 -> 35375.755 | J8: ='Cost Analysis'!N12 -> 37379.168 | ... L8: ='Cost Analysis'!P12 -> 41131.196
A9: = | B9: Gross Profit | C9: =C7-C8 -> 21163.936 | D9: =D7-D8 -> 24687.769 | E9: =E7-E8 -> 28029.845 | F9: =F7-F8 -> 31104.543 | G9: =G7-G8 -> 34508.781 | H9: =H7-H8 -> 37547.587 | I9: =I7-I8 -> 40261.646 | J9: =J7-J8 -> 42884.987 | ... L9: =L7-L8 -> 47954.852
A11: - | B11: Selling, General and Administrative Expenses | C11: ='Cost Analysis'!G16 -> 1525.5066 | D11: ='Cost Analysis'!H16 -> 1725.4244 | E11: ='Cost Analysis'!I16 -> 1898.067 | F11: ='Cost Analysis'!J16 -> 2039.1684 | G11: ='Cost Analysis'!K16 -> 2188.4599 | H11: ='Cost Analysis'!L16 -> 2301.3881 | I11: ='Cost Analysis'!M16 -> 2382.8304 | J11: ='Cost Analysis'!N16 -> 2448.3244 | ... L11: ='Cost Analysis'!P16 -> 2539.2495
A12: - | B12: R&D | C12: ='Cost Analysis'!G20 -> 4516.0853 | D12: ='Cost Analysis'!H20 -> 5247.8491 | E12: ='Cost Analysis'!I20 -> 5935.5414 | F12: ='Cost Analysis'!J20 -> 6561.6032 | G12: ='Cost Analysis'!K20 -> 7252.1789 | H12: ='Cost Analysis'!L20 -> 7861.038 | I12: ='Cost Analysis'!M20 -> 8397.5877 | J12: ='Cost Analysis'!N20 -> 8911.2696 | ... L12: ='Cost Analysis'!P20 -> 9890.714
A14: = | B14: Standardised Operating Profit (EBIT) | C14: =C9-C11-C12 -> 15122.344 | D14: =D9-D11-D12 -> 17714.496 | E14: =E9-E11-E12 -> 20196.236 | F14: =F9-F11-F12 -> 22503.772 | G14: =G9-G11-G12 -> 25068.142 | H14: =H9-H11-H12 -> 27385.161 | I14: =I9-I11-I12 -> 29481.228 | J14: =J9-J11-J12 -> 31525.392 | ... L14: =L9-L11-L12 -> 35524.888
B15: Finance Income
A16: - | B16: Finance Costs | C16: ='Statement of Profit or Loss'!$E$25 -> -118.3 | D16: ='Statement of Profit or Loss'!$E$25 -> -118.3 | E16: ='Statement of Profit or Loss'!$E$25 -> -118.3 | F16: ='Statement of Profit or Loss'!$E$25 -> -118.3 | G16: ='Statement of Profit or Loss'!$E$25 -> -118.3 | H16: ='Statement of Profit or Loss'!$E$25 -> -118.3 | I16: ='Statement of Profit or Loss'!$E$25 -> -118.3 | J16: ='Statement of Profit or Loss'!$E$25 -> -118.3 | ... L16: ='Statement of Profit or Loss'!$E$25 -> -118.3
A17: = | B17: Profit Before Tax | C17: =SUM(C14:C16) -> 15004.044 | D17: =SUM(D14:D16) -> 17596.196 | E17: =SUM(E14:E16) -> 20077.936 | F17: =SUM(F14:F16) -> 22385.472 | G17: =SUM(G14:G16) -> 24949.842 | H17: =SUM(H14:H16) -> 27266.861 | I17: =SUM(I14:I16) -> 29362.928 | J17: =SUM(J14:J16) -> 31407.092 | ... L17: =SUM(L14:L16) -> 35406.588
A18: - | B18: Income Tax Expense | C18: =C17*$N$7 -> 3871.0434 | D18: =D17*$N$7 -> 4539.8185 | E18: =E17*$N$7 -> 5180.1075 | F18: =F17*$N$7 -> 5775.4517 | G18: =G17*$N$7 -> 6437.0593 | H18: =H17*$N$7 -> 7034.85 | I18: =I17*$N$7 -> 7575.6354 | J18: =J17*$N$7 -> 8103.0299 | ... L18: =L17*$N$7 -> 9134.8998
A19: = | B19: Profit for the Year | C19: =C17-C18 -> 11133.001 | D19: =D17-D18 -> 13056.377 | E19: =E17-E18 -> 14897.829 | F19: =F17-F18 -> 16610.02 | G19: =G17-G18 -> 18512.783 | H19: =H17-H18 -> 20232.011 | I19: =I17-I18 -> 21787.293 | J19: =J17-J18 -> 23304.063 | ... L19: =L17-L18 -> 26271.689
B24: Cash Flow Statement | C24: Forecast Period
C25: 2026 E | D25: 2027 E | E25: 2028 E | F25: 2029 E | G25: 2030 E | H25: 2031 E | I25: 2032 E | J25: 2033 E | K25: 2034 E | L25: 2035 E
B26: Operating Activities
B27: Net Profit | C27: =C19 -> 11133.001 | D27: =D19 -> 13056.377 | E27: =E19 -> 14897.829 | F27: =F19 -> 16610.02 | G27: =G19 -> 18512.783 | H27: =H19 -> 20232.011 | I27: =I19 -> 21787.293 | J27: =J19 -> 23304.063 | ... L27: =L19 -> 26271.689
A28: + | B28: Depreciation and Amortisation | C28: ='Cost Analysis'!G32 -> 1140.5818 | D28: ='Cost Analysis'!H32 -> 1325.3959 | E28: ='Cost Analysis'!I32 -> 1499.0794 | F28: ='Cost Analysis'!J32 -> 1657.1974 | G28: ='Cost Analysis'!K32 -> 1831.6091 | H28: ='Cost Analysis'!L32 -> 1985.3824 | I28: ='Cost Analysis'!M32 -> 2120.8934 | J28: ='Cost Analysis'!N32 -> 2250.6288 | ... L28: ='Cost Analysis'!P32 -> 2497.9971
A29: - | B29: Change in Net Working Capital | C29: ='Balance Sheet'!F84 -> 4889.1998 | D29: ='Balance Sheet'!G84 -> 1732.2026 | E29: ='Balance Sheet'!H84 -> 1627.8782 | F29: ='Balance Sheet'!I84 -> 1481.9889 | G29: ='Balance Sheet'!J84 -> 1634.7037 | H29: ='Balance Sheet'!K84 -> 1441.2673 | I29: ='Balance Sheet'!L84 -> 1270.0994 | J29: ='Balance Sheet'!M84 -> 1215.9678 | ... L29: ='Balance Sheet'!O84 -> 1135.6669
A30: + | B30: Finance Costs | C30: =-C16 -> 118.3 | D30: =-D16 -> 118.3 | E30: =-E16 -> 118.3 | F30: =-F16 -> 118.3 | G30: =-G16 -> 118.3 | H30: =-H16 -> 118.3 | I30: =-I16 -> 118.3 | J30: =-J16 -> 118.3 | ... L30: =-L16 -> 118.3
A31: = | B31: Net Cash from Operating Activities | C31: =C27+C28-C29+C30 -> 7502.6828 | D31: =D27+D28-D29+D30 -> 12767.871 | E31: =E27+E28-E29+E30 -> 14887.33 | F31: =F27+F28-F29+F30 -> 16903.529 | G31: =G27+G28-G29+G30 -> 18827.989 | H31: =H27+H28-H29+H30 -> 20894.426 | I31: =I27+I28-I29+I30 -> 22756.386 | J31: =J27+J28-J29+J30 -> 24457.024 | ... L31: =L27+L28-L29+L30 -> 27752.319
B33: Investing Activities
A34: - | B34: Capital Expenditure (Capex) | C34: ='Cash Flow'!F79 -> 2644.684 | D34: ='Cash Flow'!G79 -> 3073.2153 | E34: ='Cash Flow'!H79 -> 3475.9378 | F34: ='Cash Flow'!I79 -> 3842.5685 | G34: ='Cash Flow'!J79 -> 4246.9795 | H34: ='Cash Flow'!K79 -> 4603.536 | I34: ='Cash Flow'!L79 -> 4917.7472 | J34: ='Cash Flow'!M79 -> 5218.5667 | ... L34: ='Cash Flow'!O79 -> 5792.1433
B36: Financing Activities
A37: + | B37: Proceeds from / Repayment of Debt
A38: - | B38: Finance Costs | C38: =C16 -> -118.3 | D38: =D16 -> -118.3 | E38: =E16 -> -118.3 | F38: =F16 -> -118.3 | G38: =G16 -> -118.3 | H38: =H16 -> -118.3 | I38: =I16 -> -118.3 | J38: =J16 -> -118.3 | ... L38: =L16 -> -118.3
A39: - | B39: Share Buybacks and Cancellation | C39: ='Cash Flow'!F69 -> -4150.1961 | D39: ='Cash Flow'!G69 -> -4867.1986 | E39: ='Cash Flow'!H69 -> -5553.6608 | F39: ='Cash Flow'!I69 -> -6191.9371 | G39: ='Cash Flow'!J69 -> -6901.2553 | H39: ='Cash Flow'!K69 -> -7542.1545 | I39: ='Cash Flow'!L69 -> -8121.9375 | J39: ='Cash Flow'!M69 -> -8687.364 | ... L39: ='Cash Flow'!O69 -> -9793.6452
A40: - | B40: Dividends Paid | C40: ='Cash Flow'!F68 -> -3432.0503 | D40: ='Cash Flow'!G68 -> -4024.9834 | E40: ='Cash Flow'!H68 -> -4592.6608 | F40: ='Cash Flow'!I68 -> -5120.4904 | G40: ='Cash Flow'!J68 -> -5707.0688 | H40: ='Cash Flow'!K68 -> -6237.0675 | I40: ='Cash Flow'!L68 -> -6716.5254 | J40: ='Cash Flow'!M68 -> -7184.1111 | ... L40: ='Cash Flow'!O68 -> -8098.9625
A41: + | B41: Capital Contributions (raising new equity)
A42: = | B42: Net Cash from Financing Activities | C42: =C37+C38+C39+C40+C41 -> -7700.5464 | D42: =D37+D38+D39+D40+D41 -> -9010.482 | E42: =E37+E38+E39+E40+E41 -> -10264.622 | F42: =F37+F38+F39+F40+F41 -> -11430.728 | G42: =G37+G38+G39+G40+G41 -> -12726.624 | H42: =H37+H38+H39+H40+H41 -> -13897.522 | I42: =I37+I38+I39+I40+I41 -> -14956.763 | J42: =J37+J38+J39+J40+J41 -> -15989.775 | ... L42: =L37+L38+L39+L40+L41 -> -18010.908
A44: = | B44: Net Change in Cash and Cash Equivalents | C44: =C42-C34+C31 -> -2842.5476 | D44: =D42-D34+D31 -> 684.17325 | E44: =E42-E34+E31 -> 1146.7703 | F44: =F42-F34+F31 -> 1630.2326 | G44: =G42-G34+G31 -> 1854.3849 | H44: =H42-H34+H31 -> 2393.3678 | I44: =I42-I34+I31 -> 2881.8764 | J44: =J42-J34+J31 -> 3248.6819 | ... L44: =L42-L34+L31 -> 3949.2678
A45: + | B45: Cash and Cash Equivalents at the Beginning of the Year | C45: ='Balance Sheet'!E24 -> 12916 | D45: =C46 -> 10073.452 | E45: =D46 -> 10757.626 | F45: =E46 -> 11904.396 | G45: =F46 -> 13534.629 | H45: =G46 -> 15389.013 | I45: =H46 -> 17782.381 | J45: =I46 -> 20664.258 | K45: =J46 -> 23912.939 | L45: =K46 -> 27506.851
A46: = | B46: Cash and Cash Equivalents at the End of the Year | C46: =C44+C45 -> 10073.452 | D46: =D44+D45 -> 10757.626 | E46: =E44+E45 -> 11904.396 | F46: =F44+F45 -> 13534.629 | G46: =G44+G45 -> 15389.013 | H46: =H44+H45 -> 17782.381 | I46: =I44+I45 -> 20664.258 | J46: =J44+J45 -> 23912.939 | ... L46: =L44+L45 -> 31456.119
B50: Balance Sheet | C50: Forecast Period
C51: 2026 E | D51: 2027 E | E51: 2028 E | F51: 2029 E | G51: 2030 E | H51: 2031 E | I51: 2032 E | J51: 2033 E | K51: 2034 E | L51: 2035 E
B53: Current Assets | C53: ='Balance Sheet'!F73 -> 40048.087 | D53: ='Balance Sheet'!G73 -> 46537.278 | E53: ='Balance Sheet'!H73 -> 52635.649 | F53: ='Balance Sheet'!I73 -> 58187.488 | G53: ='Balance Sheet'!J73 -> 64311.428 | H53: ='Balance Sheet'!K73 -> 69710.715 | I53: ='Balance Sheet'!L73 -> 74468.771 | J53: ='Balance Sheet'!M73 -> 79024.039 | ... L53: ='Balance Sheet'!O73 -> 87709.631
B55: Non-current Assets | C55: ='Balance Sheet'!F101 -> 30709.746 | D55: ='Balance Sheet'!G101 -> 35685.799 | E55: ='Balance Sheet'!H101 -> 40362.162 | F55: ='Balance Sheet'!I101 -> 44619.433 | G55: ='Balance Sheet'!J101 -> 49315.403 | H55: ='Balance Sheet'!K101 -> 53455.694 | I55: ='Balance Sheet'!L101 -> 57104.276 | J55: ='Balance Sheet'!M101 -> 60597.354 | ... L55: ='Balance Sheet'!O101 -> 67257.655
B57: Total Assets | C57: =C55+C53 -> 70757.833 | D57: =D55+D53 -> 82223.077 | E57: =E55+E53 -> 92997.811 | F57: =F55+F53 -> 102806.92 | G57: =G55+G53 -> 113626.83 | H57: =H55+H53 -> 123166.41 | I57: =I55+I53 -> 131573.05 | J57: =J55+J53 -> 139621.39 | ... L57: =L55+L53 -> 154967.29
B60: Current Liabilities | C60: ='Balance Sheet'!F77 -> 29357.787 | D60: ='Balance Sheet'!G77 -> 34114.776 | E60: ='Balance Sheet'!H77 -> 38585.268 | F60: ='Balance Sheet'!I77 -> 42655.118 | G60: ='Balance Sheet'!J77 -> 47144.354 | H60: ='Balance Sheet'!K77 -> 51102.374 | I60: ='Balance Sheet'!L77 -> 54590.331 | J60: ='Balance Sheet'!M77 -> 57929.632 | ... L60: ='Balance Sheet'!O77 -> 64296.721
B62: Non-current Liabilities | C62: ='Balance Sheet'!F95 -> 14546.036 | D62: ='Balance Sheet'!G95 -> 16903.003 | E62: ='Balance Sheet'!H95 -> 19118.018 | F62: ='Balance Sheet'!I95 -> 21134.525 | G62: ='Balance Sheet'!J95 -> 23358.827 | H62: ='Balance Sheet'!K95 -> 25319.925 | I62: ='Balance Sheet'!L95 -> 27048.119 | J62: ='Balance Sheet'!M95 -> 28702.658 | ... L62: ='Balance Sheet'!O95 -> 31857.388
B64: Total Liabilities | C64: =C62+C60 -> 43903.824 | D64: =D62+D60 -> 51017.779 | E64: =E62+E60 -> 57703.286 | F64: =F62+F60 -> 63789.643 | G64: =G62+G60 -> 70503.182 | H64: =H62+H60 -> 76422.299 | I64: =I62+I60 -> 81638.45 | J64: =J62+J60 -> 86632.289 | ... L64: =L62+L60 -> 96154.11
B66: Equity | C66: ='Balance Sheet'!F109 -> 26854.009 | D66: ='Balance Sheet'!G109 -> 31205.298 | E66: ='Balance Sheet'!H109 -> 35294.525 | F66: ='Balance Sheet'!I109 -> 39017.277 | G66: ='Balance Sheet'!J109 -> 43123.649 | H66: ='Balance Sheet'!K109 -> 46744.109 | I66: ='Balance Sheet'!L109 -> 49934.596 | J66: ='Balance Sheet'!M109 -> 52989.105 | ... L66: ='Balance Sheet'!O109 -> 58813.177
B68: Total Equity and Liabilities | C68: =C66+C64 -> 70757.833 | D68: =D66+D64 -> 82223.077 | E68: =E66+E64 -> 92997.811 | F68: =F66+F64 -> 102806.92 | G68: =G66+G64 -> 113626.83 | H68: =H66+H64 -> 123166.41 | I68: =I66+I64 -> 131573.05 | J68: =J66+J64 -> 139621.39 | ... L68: =L66+L64 -> 154967.29

Sheet WACC
B7: ASML Holdings
B8: Beta | C8: 1.37
B9: rf | C9: 0.03315
B10: rm
B11: (rm - rf) | C11: 0.0423
G12: Blume adjusted beta | H12: =(2/3) * C8 + (1/3) * 1 -> 1.2466667
B13: re (cost of equity) | C13: =C9+C8*(C11) -> 0.091101
B20: Bu for retailers
B21: Beta = Bu x (1+(1-T) x D/E)
B24: beta | E24: =H12 -> 1.2466667 | F24: 1.37 | G24: blume adjusted beta vs current company beta
B25: risk free rate | E25: =C9 -> 0.03315 | F25: =C9 -> 0.03315
B26: market risk premium (rm-rf) | E26: =C11 -> 0.0423 | F26: =E26 -> 0.0423
B27: cost of equity | E27: =E25+E24*E26 -> 0.085884 | F27: =C13 -> 0.091101
B28: capitalization ( E) | F28: 563419
B29: IBD (interest-bearing debt, latest balance sheet) | F29: ='Balance Sheet'!$E$59+'Balance Sheet'!$E$45 -> 4390.9
B30: E/(E+D) | F30: =F28/(F28+F29) -> 0.99226695
B31: D/(E+D) | F31: =F29/(F28+F29) -> 0.0077330459
B32: Interest coverage ratio | F32: =-1*'Statement of Profit or Loss'!E22/'Statement of Profit or Loss'!E25 -> 101.89349
B33: Default Spread / Credit Risk Spread | F33: 0.0111
B34: cost of debt | F34: 0.0574
B35: marginal tax rate (CIT in Netherlands) | F35: ='DCF Model'!O4 -> 0.258
C36: WACC | E36: =$F$30*E27+$F$31*$F$34*(1-$F$35) -> 0.085549212 | F36: =$F$30*F27+$F$31*$F$34*(1-$F$35) -> 0.090725868

Sheet Cost Analysis
C2: 2022 | D2: 2023 | E2: 2024 | F2: 2025 | G2: 2026 E | H2: 2027 E | I2: 2028 E | J2: 2029 E | K2: 2030 E | L2: 2031 E | M2: 2032 E | N2: 2033 E | O2: 2034 E | P2: 2035 E
B3: Revenue | C3: ='ASML Revenue Model'!C7 -> 21173.4 | D3: ='ASML Revenue Model'!D7 -> 27558.5 | E3: ='ASML Revenue Model'!E7 -> 28262.9 | F3: ='ASML Revenue Model'!F7 -> 32667.3 | G3: ='ASML Revenue Model'!G7 -> 40676.557 | H3: ='ASML Revenue Model'!H7 -> 47267.583 | I3: ='ASML Revenue Model'!I7 -> 53461.654 | J3: ='ASML Revenue Model'!J7 -> 59100.617 | ... P3: ='ASML Revenue Model'!P7 -> 89086.048
B4: YoY Growth | D4: =D3/C3-1 -> 0.30156234 | E4: =E3/D3-1 -> 0.025560172 | F4: =F3/E3-1 -> 0.1558368 | G4: =G3/F3-1 -> 0.24517659 | H4: =H3/G3-1 -> 0.16203499 | I4: =I3/H3-1 -> 0.1310427 | J4: =J3/I3-1 -> 0.10547678 | K4: =K3/J3-1 -> 0.10524496 | ... P4: =P3/O3-1 -> 0.050978793
B7: Cost Analysis | C7: 2022 | D7: 2023 | E7: 2024 | F7: 2025 | G7: 2026 E | H7: 2027 E | I7: 2028 E | J7: 2029 E | K7: 2030 E | L7: 2031 E | M7: 2032 E | N7: 2033 E | O7: 2034 E | P7: 2035 E
B8: Cost of System Sales | C8: 7843.3 | D8: 10439.1 | E8: 10615.1 | F8: 11710.6 | G8: =G3*G9 -> 14500.412 | H8: =H3*H9 -> 16755.451 | I8: =I3*I9 -> 18844.207 | J8: =J3*J9 -> 20713.632 | K8: =K3*K9 -> 22762.996 | L8: =L3*L9 -> 24532.461 | M8: =M3*M9 -> 26055.633 | N8: =N3*N9 -> 27488.932 | ... P8: =P3*P9 -> 30153.917
B9: Cost of System Sales / Revenue | C9: =C8/C3 -> 0.37043177 | D9: =D8/D3 -> 0.37879783 | E9: =E8/E3 -> 0.37558425 | F9: =F8/F3 -> 0.3584808 | G9: =F9-0.002 -> 0.3564808 | H9: =G9-0.002 -> 0.3544808 | I9: =H9-0.002 -> 0.3524808 | J9: =I9-0.002 -> 0.3504808 | K9: =J9-0.002 -> 0.3484808 | L9: =K9-0.002 -> 0.3464808 | M9: =L9-0.002 -> 0.3444808 | N9: =M9-0.002 -> 0.3424808 | ... P9: =O9-0.002 -> 0.3384808
B10: Cost of Servie & Field Option Sales | C10: 2817.4 | D10: 3345 | E10: 3364 | F10: 4025.3 | G10: =G3*G11 -> 5012.2093 | H10: =H3*H11 -> 5824.3626 | I10: =I3*I11 -> 6587.6028 | J10: =J3*J11 -> 7282.4419 | K10: =K3*K11 -> 8048.8822 | L10: =L3*L11 -> 8724.6288 | M10: =M3*M11 -> 9320.1223 | N10: =N3*N11 -> 9890.2359 | ... P10: =P3*P11 -> 10977.279
B11: Cost of Servie & Field Option Sales / Revenue | C11: =C10/C3 -> 0.13306318 | D11: =D10/D3 -> 0.12137816 | E11: =E10/E3 -> 0.11902529 | F11: =F10/F3 -> 0.12322108 | G11: =F11 -> 0.12322108 | H11: =G11 -> 0.12322108 | I11: =H11 -> 0.12322108 | J11: =I11 -> 0.12322108 | K11: =J11 -> 0.12322108 | L11: =K11 -> 0.12322108 | M11: =L11 -> 0.12322108 | N11: =M11 -> 0.12322108 | ... P11: =O11 -> 0.12322108 | R11: Total Cost of Sales Delta
B12: Total Cost of Sales | C12: =SUM(C8+C10) -> 10660.7 | D12: =SUM(D8+D10) -> 13784.1 | E12: =SUM(E8+E10) -> 13979.1 | F12: =SUM(F8+F10) -> 15735.9 | G12: =(G10+G8)*(1+$R$12) -> 19512.621 | H12: =(H10+H8)*(1+$R$12) -> 22579.813 | I12: =(I10+I8)*(1+$R$12) -> 25431.81 | J12: =(J10+J8)*(1+$R$12) -> 27996.074 | K12: =(K10+K8)*(1+$R$12) -> 30811.878 | L12: =(L10+L8)*(1+$R$12) -> 33257.09 | M12: =(M10+M8)*(1+$R$12) -> 35375.755 | N12: =(N10+N8)*(1+$R$12) -> 37379.168 | ... P12: =(P10+P8)*(1+$R$12) -> 41131.196
B13: Cost of Sales / Revenue (Gross Margin driver) | C13: =C12/C3 -> 0.50349495 | D13: =D12/D3 -> 0.50017599 | E13: =E12/E3 -> 0.49460954 | F13: =F12/F3 -> 0.48170189 | G13: =G12/G3 -> 0.47970189 | H13: =H12/H3 -> 0.47770189 | I13: =I12/I3 -> 0.47570189 | J13: =J12/J3 -> 0.47370189 | ... P13: =P12/P3 -> 0.46170189
C15: 2022 | D15: 2023 | E15: 2024 | F15: 2025 | G15: 2026 E | H15: 2027 E | I15: 2028 E | J15: 2029 E | K15: 2030 E | L15: 2031 E | M15: 2032 E | N15: 2033 E | O15: 2034 E | P15: 2035 E
B16: Selling, general and administrative (SG&A) costs | C16: 909.6 | D16: 1149.4 | E16: 1165.7 | F16: 1257.8 | G16: =G17*G3 -> 1525.5066 | H16: =H17*H3 -> 1725.4244 | I16: =I17*I3 -> 1898.067 | J16: =J17*J3 -> 2039.1684 | K16: =K17*K3 -> 2188.4599 | L16: =L17*L3 -> 2301.3881 | M16: =M17*M3 -> 2382.8304 | N16: =N17*N3 -> 2448.3244 | ... P16: =P17*P3 -> 2539.2495
B17: SG&A / Revenue | C17: =C16/C3 -> 0.042959562 | D17: =D16/D3 -> 0.04170764 | E17: =E16/E3 -> 0.041244883 | F17: =F16/F3 -> 0.038503335 | G17: =F17-0.001 -> 0.037503335 | H17: =G17-0.001 -> 0.036503335 | I17: =H17-0.001 -> 0.035503335 | J17: =I17-0.001 -> 0.034503335 | K17: =J17-0.001 -> 0.033503335 | L17: =K17-0.001 -> 0.032503335 | M17: =L17-0.001 -> 0.031503335 | N17: =M17-0.001 -> 0.030503335 | ... P17: =O17-0.001 -> 0.028503335
C19: 2022 | D19: 2023 | E19: 2024 | F19: 2025 | G19: 2026 E | H19: 2027 E | I19: 2028 E | J19: 2029 E | K19: 2030 E | L19: 2031 E | M19: 2032 E | N19: 2033 E | O19: 2034 E | P19: 2035 E
B20: R&D Costs | C20: 2282.1 | D20: 3113.1 | E20: 3181 | F20: 3619.6 | G20: =G21*G3 -> 4516.0853 | H20: =H21*H3 -> 5247.8491 | I20: =I21*I3 -> 5935.5414 | J20: =J21*J3 -> 6561.6032 | K20: =K21*K3 -> 7252.1789 | L20: =L21*L3 -> 7861.038 | M20: =M21*M3 -> 8397.5877 | N20: =N21*N3 -> 8911.2696 | ... P20: =P21*P3 -> 9890.714
B21: R&D/ Revenue | C21: =C20/C3 -> 0.10778146 | D21: =D20/D3 -> 0.11296333 | E21: =E20/E3 -> 0.11255038 | F21: =F20/F3 -> 0.11080193 | G21: =AVERAGE(C21:F21) -> 0.11102428 | H21: =G21 -> 0.11102428 | I21: =H21 -> 0.11102428 | J21: =I21 -> 0.11102428 | K21: =J21 -> 0.11102428 | L21: =K21 -> 0.11102428 | M21: =L21 -> 0.11102428 | N21: =M21 -> 0.11102428 | O21: =N21 -> 0.11102428 | P21: =O21 -> 0.11102428
C23: 2022 | D23: 2023 | E23: 2024 | F23: 2025 | G23: 2026 E | H23: 2027 E | I23: 2028 E | J23: 2029 E | K23: 2030 E | L23: 2031 E | M23: 2032 E | N23: 2033 E | O23: 2034 E | P23: 2035 E
B24: Total Operating Expenses | C24: =C20+C16 -> 3191.7 | D24: =D20+D16 -> 4262.5 | E24: =E20+E16 -> 4346.7 | F24: =F20+F16 -> 4877.4 | G24: =G20+G16 -> 6041.5919 | H24: =H20+H16 -> 6973.2735 | I24: =I20+I16 -> 7833.6085 | J24: =J20+J16 -> 8600.7716 | ... P24: =P20+P16 -> 12429.963
B25: Total Operating Expenses/Revenue | C25: =C24/C3 -> 0.15074102 | D25: =D24/D3 -> 0.15467097 | E25: =E24/E3 -> 0.15379526 | F25: =F24/F3 -> 0.14930527 | G25: =G24/G3 -> 0.14852761 | H25: =H24/H3 -> 0.14752761 | I25: =I24/I3 -> 0.14652761 | J25: =J24/J3 -> 0.14552761 | ... P25: =P24/P3 -> 0.13952761
C27: 2022 | D27: 2023 | E27: 2024 | F27: 2025 | G27: 2026 E | H27: 2027 E | I27: 2028 E | J27: 2029 E | K27: 2030 E | L27: 2031 E | M27: 2032 E | N27: 2033 E | O27: 2034 E | P27: 2035 E
B28: EBIT | C28: =C3-C24-C12 -> 7321 | D28: =D3-D24-D12 -> 9511.9 | E28: =E3-E24-E12 -> 9937.1 | F28: =F3-F24-F12 -> 12054 | G28: =G3-G24-G12 -> 15122.344 | H28: =H3-H24-H12 -> 17714.496 | I28: =I3-I24-I12 -> 20196.236 | J28: =J3-J24-J12 -> 22503.772 | ... P28: =P3-P24-P12 -> 35524.888
B29: EBIT margin | C29: =(C28/C3) -> 0.34576402 | D29: =D28/D3 -> 0.34515304 | E29: =E28/E3 -> 0.3515952 | F29: =F28/F3 -> 0.36899285 | G29: =G28/G3 -> 0.3717705 | H29: =H28/H3 -> 0.3747705 | I29: =I28/I3 -> 0.3777705 | J29: =J28/J3 -> 0.3807705 | K29: =K28/K3 -> 0.3837705 | ... P29: =P28/P3 -> 0.3987705
C31: 2022 | D31: 2023 | E31: 2024 | F31: 2025 | G31: 2026 E | H31: 2027 E | I31: 2028 E | J31: 2029 E | K31: 2030 E | L31: 2031 E | M31: 2032 E | N31: 2033 E | O31: 2034 E | P31: 2035 E
B32: Depreciation | C32: 445.2 | D32: 605.6 | E32: 787.3 | F32: 916 | G32: =G33*G3 -> 1140.5818 | H32: =H33*H3 -> 1325.3959 | I32: =I33*I3 -> 1499.0794 | J32: =J33*J3 -> 1657.1974 | K32: =K33*K3 -> 1831.6091 | L32: =L33*L3 -> 1985.3824 | M32: =M33*M3 -> 2120.8934 | N32: =N33*N3 -> 2250.6288 | ... P32: =P33*P3 -> 2497.9971
B33: Depreciation/Revenue | C33: =C32/C3 -> 0.021026382 | D33: =D32/D3 -> 0.021975071 | E33: =E32/E3 -> 0.027856306 | F33: =F32/F3 -> 0.028040273 | G33: =F33 -> 0.028040273 | H33: =G33 -> 0.028040273 | I33: =H33 -> 0.028040273 | J33: =I33 -> 0.028040273 | K33: =J33 -> 0.028040273 | L33: =K33 -> 0.028040273 | M33: =L33 -> 0.028040273 | N33: =M33 -> 0.028040273 | ... P33: =O33 -> 0.028040273
C35: 2022 | D35: 2023 | E35: 2024 | F35: 2025 | G35: 2026 E | H35: 2027 E | I35: 2028 E | J35: 2029 E | K35: 2030 E | L35: 2031 E | M35: 2032 E | N35: 2033 E | O35: 2034 E | P35: 2035 E
B36: EBITDA | C36: =C28+C32 -> 7766.2 | D36: =D28+D32 -> 10117.5 | E36: =E28+E32 -> 10724.4 | F36: =F28+F32 -> 12970 | G36: =G28+G32 -> 16262.926 | H36: =H28+H32 -> 19039.892 | I36: =I28+I32 -> 21695.315 | J36: =J28+J32 -> 24160.969 | ... P36: =P28+P32 -> 38022.885
B37: EBITDA margin | C37: =C36/C3 -> 0.36679041 | D37: =D36/D3 -> 0.36712811 | E37: =E36/E3 -> 0.37945151 | F37: =F36/F3 -> 0.39703312 | G37: =G36/G3 -> 0.39981078 | H37: =H36/H3 -> 0.40281078 | I37: =I36/I3 -> 0.40581078 | J37: =J36/J3 -> 0.40881078 | ... P37: =P36/P3 -> 0.42681078

Sheet Profitability Analysis
C2: 2022 | D2: 2023 | E2: 2024 | F2: 2025 | G2: 2026 E | H2: 2027 E | I2: 2028 E | J2: 2029 E | K2: 2030 E | L2: 2031 E | M2: 2032 E | N2: 2033 E | O2: 2034 E | P2: 2035 E
B3: Revenue | C3: ='ASML Revenue Model'!C7 -> 21173.4 | D3: ='ASML Revenue Model'!D7 -> 27558.5 | E3: ='ASML Revenue Model'!E7 -> 28262.9 | F3: ='ASML Revenue Model'!F7 -> 32667.3 | G3: ='ASML Revenue Model'!G7 -> 40676.557 | H3: ='ASML Revenue Model'!H7 -> 47267.583 | I3: ='ASML Revenue Model'!I7 -> 53461.654 | J3: ='ASML Revenue Model'!J7 -> 59100.617 | ... P3: ='ASML Revenue Model'!P7 -> 89086.048
B4: YoY Growth | D4: =D3/C3-1 -> 0.30156234 | E4: =E3/D3-1 -> 0.025560172 | F4: =F3/E3-1 -> 0.1558368 | G4: =G3/F3-1 -> 0.24517659 | H4: =H3/G3-1 -> 0.16203499 | I4: =I3/H3-1 -> 0.1310427 | J4: =J3/I3-1 -> 0.10547678 | K4: =K3/J3-1 -> 0.10524496 | ... P4: =P3/O3-1 -> 0.050978793
C7: 2022 | D7: 2023 | E7: 2024 | F7: 2025 | G7: 2026 E | H7: 2027 E | I7: 2028 E | J7: 2029 E | K7: 2030 E | L7: 2031 E | M7: 2032 E | N7: 2033 E | O7: 2034 E | P7: 2035 E
B8: Cost of System Sales | C8: ='Cost Analysis'!C8 -> 7843.3 | D8: ='Cost Analysis'!D8 -> 10439.1 | E8: ='Cost Analysis'!E8 -> 10615.1 | F8: ='Cost Analysis'!F8 -> 11710.6 | G8: ='Cost Analysis'!G8 -> 14500.412 | H8: ='Cost Analysis'!H8 -> 16755.451 | I8: ='Cost Analysis'!I8 -> 18844.207 | J8: ='Cost Analysis'!J8 -> 20713.632 | ... P8: ='Cost Analysis'!P8 -> 30153.917
B9: Cost of Servie & Field Option Sales | C9: ='Cost Analysis'!C10 -> 2817.4 | D9: ='Cost Analysis'!D10 -> 3345 | E9: ='Cost Analysis'!E10 -> 3364 | F9: ='Cost Analysis'!F10 -> 4025.3 | G9: ='Cost Analysis'!G10 -> 5012.2093 | H9: ='Cost Analysis'!H10 -> 5824.3626 | I9: ='Cost Analysis'!I10 -> 6587.6028 | J9: ='Cost Analysis'!J10 -> 7282.4419 | ... P9: ='Cost Analysis'!P10 -> 10977.279
B10: Total Cost of Sales | C10: =SUM(C8+C9) -> 10660.7 | D10: =SUM(D8+D9) -> 13784.1 | E10: =SUM(E8+E9) -> 13979.1 | F10: =SUM(F8+F9) -> 15735.9 | G10: =SUM(G8+G9) -> 19512.621 | H10: =SUM(H8+H9) -> 22579.813 | I10: =SUM(I8+I9) -> 25431.81 | J10: =SUM(J8+J9) -> 27996.074 | ... P10: =SUM(P8+P9) -> 41131.196
B11: Cost of Sales / Revenue (Gross Margin driver) | C11: =C10/C3 -> 0.50349495 | D11: =D10/D3 -> 0.50017599 | E11: =E10/E3 -> 0.49460954 | F11: =F10/F3 -> 0.48170189 | G11: =G10/G3 -> 0.47970189 | H11: =H10/H3 -> 0.47770189 | I11: =I10/I3 -> 0.47570189 | J11: =J10/J3 -> 0.47370189 | ... P11: =P10/P3 -> 0.46170189
C13: 2022 | D13: 2023 | E13: 2024 | F13: 2025 | G13: 2026 E | H13: 2027 E | I13: 2028 E | J13: 2029 E | K13: 2030 E | L13: 2031 E | M13: 2032 E | N13: 2033 E | O13: 2034 E | P13: 2035 E
B14: Selling, general and administrative (SG&A) costs | C14: ='Cost Analysis'!C16 -> 909.6 | D14: ='Cost Analysis'!D16 -> 1149.4 | E14: ='Cost Analysis'!E16 -> 1165.7 | F14: ='Cost Analysis'!F16 -> 1257.8 | G14: ='Cost Analysis'!G16 -> 1525.5066 | H14: ='Cost Analysis'!H16 -> 1725.4244 | I14: ='Cost Analysis'!I16 -> 1898.067 | J14: ='Cost Analysis'!J16 -> 2039.1684 | ... P14: ='Cost Analysis'!P16 -> 2539.2495
B15: SG&A / Revenue | C15: =C14/C3 -> 0.042959562 | D15: =D14/D3 -> 0.04170764 | E15: =E14/E3 -> 0.041244883 | F15: =F14/F3 -> 0.038503335 | G15: =G14/G3 -> 0.037503335 | H15: =H14/H3 -> 0.036503335 | I15: =I14/I3 -> 0.035503335 | J15: =J14/J3 -> 0.034503335 | ... P15: =P14/P3 -> 0.028503335
C17: 2022 | D17: 2023 | E17: 2024 | F17: 2025 | G17: 2026 E | H17: 2027 E | I17: 2028 E | J17: 2029 E | K17: 2030 E | L17: 2031 E | M17: 2032 E | N17: 2033 E | O17: 2034 E | P17: 2035 E
B18: R&D Costs | C18: ='Cost Analysis'!C20 -> 2282.1 | D18: ='Cost Analysis'!D20 -> 3113.1 | E18: ='Cost Analysis'!E20 -> 3181 | F18: ='Cost Analysis'!F20 -> 3619.6 | G18: ='Cost Analysis'!G20 -> 4516.0853 | H18: ='Cost Analysis'!H20 -> 5247.8491 | I18: ='Cost Analysis'!I20 -> 5935.5414 | J18: ='Cost Analysis'!J20 -> 6561.6032 | ... P18: ='Cost Analysis'!P20 -> 9890.714
B19: R&D/ Revenue | C19: =C18/C3 -> 0.10778146 | D19: =D18/D3 -> 0.11296333 | E19: =E18/E3 -> 0.11255038 | F19: =F18/F3 -> 0.11080193 | G19: =G18/G3 -> 0.11102428 | H19: =H18/H3 -> 0.11102428 | I19: =I18/I3 -> 0.11102428 | J19: =J18/J3 -> 0.11102428 | ... P19: =P18/P3 -> 0.11102428
C21: 2022 | D21: 2023 | E21: 2024 | F21: 2025 | G21: 2026 E | H21: 2027 E | I21: 2028 E | J21: 2029 E | K21: 2030 E | L21: 2031 E | M21: 2032 E | N21: 2033 E | O21: 2034 E | P21: 2035 E
B22: Total Operating Expenses | C22: =C18+C14 -> 3191.7 | D22: =D18+D14 -> 4262.5 | E22: =E18+E14 -> 4346.7 | F22: =F18+F14 -> 4877.4 | G22: =G18+G14 -> 6041.5919 | H22: =H18+H14 -> 6973.2735 | I22: =I18+I14 -> 7833.6085 | J22: =J18+J14 -> 8600.7716 | ... P22: =P18+P14 -> 12429.963
B23: Total Operating Expenses/Revenue | C23: =C22/C3 -> 0.15074102 | D23: =D22/D3 -> 0.15467097 | E23: =E22/E3 -> 0.15379526 | F23: =F22/F3 -> 0.14930527 | G23: =G22/G3 -> 0.14852761 | H23: =H22/H3 -> 0.14752761 | I23: =I22/I3 -> 0.14652761 | J23: =J22/J3 -> 0.14552761 | ... P23: =P22/P3 -> 0.13952761
C26: 2022 | D26: 2023 | E26: 2024 | F26: 2025 | G26: 2026 E | H26: 2027 E | I26: 2028 E | J26: 2029 E | K26: 2030 E | L26: 2031 E | M26: 2032 E | N26: 2033 E | O26: 2034 E | P26: 2035 E
B27: EBIT | C27: =C3-C22-C10 -> 7321 | D27: =D3-D22-D10 -> 9511.9 | E27: =E3-E22-E10 -> 9937.1 | F27: =F3-F22-F10 -> 12054 | G27: =G3-G22-G10 -> 15122.344 | H27: =H3-H22-H10 -> 17714.496 | I27: =I3-I22-I10 -> 20196.236 | J27: =J3-J22-J10 -> 22503.772 | ... Q27: =Q3-Q22-Q10 -> 0
B28: EBIT margin | C28: =C27/C3 -> 0.34576402 | D28: =D27/D3 -> 0.34515304 | E28: =E27/E3 -> 0.3515952 | F28: =F27/F3 -> 0.36899285 | G28: =G27/G3 -> 0.3717705 | H28: =H27/H3 -> 0.3747705 | I28: =I27/I3 -> 0.3777705 | J28: =J27/J3 -> 0.3807705 | ... P28: =P27/P3 -> 0.3987705
B30: Net Profit Margin | C30: ='Statement of Profit or Loss'!B40 -> 0.30206769 | D30: ='Statement of Profit or Loss'!C40 -> 0.29447176 | E30: ='Statement of Profit or Loss'!D40 -> 0.29540493 | F30: ='Statement of Profit or Loss'!E40 -> 0.3126368 | G30: ='Statement of Profit or Loss'!F40 -> 0 | H30: ='Statement of Profit or Loss'!G40 -> 0 | I30: ='Statement of Profit or Loss'!H40 -> 0 | J30: ='Statement of Profit or Loss'!I40 -> 0 | ... P30: ='Statement of Profit or Loss'!O40 -> 0

Sheet Balance Sheet
A1: IFRS
A2: Please note: The content of this file is qualified in its entirety by reference to the electronic version of the ASML 2025 Annual Report based on IFRS and therefore: (i) your local (browser and/or mobile device) settings can influence the way this table and its content is being displayed and (ii) (foot)notes have been deleted for reader's convenience.
A4: Always refer to the electronic version of the ASML 2025 Annual Report based on IFRS for the full and official financial information.
A6: Consolidated Statement of Financial Position for the years ended December 31, 2022, 2023, 2024 and 2025
A8: As of December 31 (€, in millions) | B8: 2022 | C8: 2023 | D8: 2024 | E8: 2025
A10: Assets
A11: Finance receivables, net | B11: — | C11: 60.6 | D11: 317.2 | E11: 13.3
A12: Deferred tax assets | B12: 2188.9 | C12: 2104.8 | D12: 2168.6 | E12: 1811.6
A13: Loans receivable | B13: 364.4 | C13: 929.2 | D13: 1456.7 | E13: 1653.8
A14: Other assets | B14: 739.8 | C14: 640.7 | D14: 790.8 | E14: 1057.1
A15: Derivative financial instruments | B15: — | C15: 11.3 | D15: 0 | E15: 0
A16: Equity investments | C16: 0 | D16: 0 | E16: 1736.7
A17: Investments in associates | B17: 923.6 | C17: 919.6 | D17: 903 | E17: 822.6
A18: Goodwill | B18: 4577.1 | C18: 4610.1 | D18: 4610.1 | E18: 4610.1
A19: Intangible assets, net | B19: 3345.7 | C19: 3933.2 | D19: 4728.9 | E19: 5396.3
A20: Property, plant and equipment, net | B20: 3944.2 | C20: 5493.2 | D20: 6846.8 | E20: 7893.8
A21: Right-of-use assets | B21: 192.7 | C21: 306.6 | D21: 387.2 | E21: 341
A22: Total non-current assets | B22: 16276.4 | C22: 19009.3 | D22: 22209.3 | E22: 25336.3
A24: Cash and cash equivalents | B24: 7268.3 | C24: 7004.7 | D24: 12735.9 | E24: 12916
A25: Short-term investments | B25: 107.7 | C25: 5.4 | D25: 5.4 | E25: 405.9
A26: Accounts receivable, net | B26: 5323.8 | C26: 4334.1 | D26: 4477.5 | E26: 3023
A27: Finance receivables, net | B27: 1356.7 | C27: 1379.2 | D27: 82.6 | E27: 613.5
A28: Current tax assets | B28: 33.4 | C28: 1001.2 | D28: 283.6 | E28: 88.9
A29: Contract assets | B29: 131.9 | C29: 240.1 | D29: 320.6 | E29: 440.6
A30: Inventories, net | B30: 7199.7 | C30: 8850.7 | D30: 10891.5 | E30: 11429.3
A31: Loans receivable | C31: 0 | D31: 0 | E31: 266.1
A32: Other assets | B32: 1110.8 | C32: 1234.1 | D32: 1463.6 | E32: 1023.6
A33: Derivative financial instruments | B33: 17.3 | C33: 19.8 | D33: 96.5 | E33: 33.6
A34: Total current assets | B34: 22549.6 | C34: 24069.3 | D34: 30357.2 | E34: 30240.5
A35: Current assets/ revenue | B35: =B34/'ASML Revenue Model'!C7 -> 1.0649966 | C35: =C34/'ASML Revenue Model'!D7 -> 0.87338934 | D35: =D34/'ASML Revenue Model'!E7 -> 1.0741007 | E35: =E34/'ASML Revenue Model'!F7 -> 0.92571164
A39: Total assets | B39: 38826 | C39: 43078.6 | D39: 52566.5 | E39: 55576.8
A41: Equity and liabilities
A43: Shareholders’ equity | B43: 11286 | C43: 16209.5 | D43: 22021.9 | E43: 24185
A45: Long-term debt | B45: 3514.2 | C45: 4631.5 | D45: 3677.3 | E45: 2709
A46: Deferred and other income tax liabilities | B46: 538.4 | C46: 737.3 | D46: 732.9 | E46: 444.9
A47: Contract liabilities | B47: 5269.9 | C47: 4825.5 | D47: 5625.4 | E47: 3366.3
A48: Accrued and other liabilities | B48: 275.9 | C48: 338.4 | D48: 430.2 | E48: 412.3
A49: Derivative financial instruments | B49: 179 | C49: 62.7 | D49: 29.3 | E49: 19.9
A50: Total non-current liabilities | B50: 9777.4 | C50: 10595.4 | D50: 10495.1 | E50: 6952.4
A55: Accounts payable | B55: 2563.5 | C55: 2346.3 | D55: 3498.5 | E55: 3521.8
A56: Accrued and other liabilities | B56: 1574.3 | C56: 2083.4 | D56: 2602.3 | E56: 2494.2
A57: Derivative financial instruments | B57: 82.3 | C57: 94 | D57: 84.3 | E57: 73.1
A58: Current tax liabilities | B58: 315.3 | C58: 308.9 | D58: 283.3 | E58: 662.1
A59: Short-term borrowings and current portion of long-term debt | B59: 746.2 | C59: 0.1 | D59: 1010.3 | E59: 1681.9
... A61: Total current liabilities | B61: 17762.6 | C61: 16273.7 | D61: 20049.5 | E61: 24439.4
A62: Current liabilities/ revenue | B62: =B61/'ASML Revenue Model'!C7 -> 0.83891109 | C62: =C61/'ASML Revenue Model'!D7 -> 0.59051472 | D62: =D61/'ASML Revenue Model'!E7 -> 0.70939288 | E62: =E61/'ASML Revenue Model'!F7 -> 0.74813039
A66: Total equity and liabilities | B66: 38826 | C66: 43078.6 | D66: 52566.5 | E66: 55576.8
A69: Calculation for Balance Sheet Items Forecasting
B72: 2022 | C72: 2023 | D72: 2024 | E72: 2025 | F72: 2026 E | G72: 2027 E | H72: 2028 E | I72: 2029 E | J72: 2030 E | K72: 2031 E | L72: 2032 E | M72: 2033 E | N72: 2034 E | O72: 2035 E
A73: Total current assets | B73: 22549.6 | C73: 24069.3 | D73: 30357.2 | E73: 30240.5 | F73: =F74*'ASML Revenue Model'!G7 -> 40048.087 | G73: =G74*'ASML Revenue Model'!H7 -> 46537.278 | H73: =H74*'ASML Revenue Model'!I7 -> 52635.649 | I73: =I74*'ASML Revenue Model'!J7 -> 58187.488 | J73: =J74*'ASML Revenue Model'!K7 -> 64311.428 | K73: =K74*'ASML Revenue Model'!L7 -> 69710.715 | L73: =L74*'ASML Revenue Model'!M7 -> 74468.771 | M73: =M74*'ASML Revenue Model'!N7 -> 79024.039 | ... O73: =O74*'ASML Revenue Model'!P7 -> 87709.631
A74: Current assets/ revenue | B74: =B73/'ASML Revenue Model'!C7 -> 1.0649966 | C74: =C73/'ASML Revenue Model'!D7 -> 0.87338934 | D74: =D73/'ASML Revenue Model'!E7 -> 1.0741007 | E74: =E73/'ASML Revenue Model'!F7 -> 0.92571164 | F74: =AVERAGE(B74:E74) -> 0.98454958 | G74: =F74 -> 0.98454958 | H74: =G74 -> 0.98454958 | I74: =H74 -> 0.98454958 | J74: =I74 -> 0.98454958 | K74: =J74 -> 0.98454958 | L74: =K74 -> 0.98454958 | M74: =L74 -> 0.98454958 | N74: =M74 -> 0.98454958 | O74: =N74 -> 0.98454958
B76: 2022 | C76: 2023 | D76: 2024 | E76: 2025 | F76: 2026 E | G76: 2027 E | H76: 2028 E | I76: 2029 E | J76: 2030 E
A77: Total current liabilities | B77: 17762.6 | C77: 16273.7 | D77: 20049.5 | E77: 24439.4 | F77: ='ASML Revenue Model'!G7*F78 -> 29357.787 | G77: ='ASML Revenue Model'!H7*G78 -> 34114.776 | H77: ='ASML Revenue Model'!I7*H78 -> 38585.268 | I77: ='ASML Revenue Model'!J7*I78 -> 42655.118 | J77: ='ASML Revenue Model'!K7*J78 -> 47144.354 | K77: ='ASML Revenue Model'!L7*K78 -> 51102.374 | L77: ='ASML Revenue Model'!M7*L78 -> 54590.331 | M77: ='ASML Revenue Model'!N7*M78 -> 57929.632 | ... O77: ='ASML Revenue Model'!P7*O78 -> 64296.721
A78: Current liabilities/ revenue | B78: =B77/'ASML Revenue Model'!C7 -> 0.83891109 | C78: =C77/'ASML Revenue Model'!D7 -> 0.59051472 | D78: =D77/'ASML Revenue Model'!E7 -> 0.70939288 | E78: =E77/'ASML Revenue Model'!F7 -> 0.74813039 | F78: =AVERAGE(B78:E78) -> 0.72173727 | G78: =F78 -> 0.72173727 | H78: =G78 -> 0.72173727 | I78: =H78 -> 0.72173727 | J78: =I78 -> 0.72173727 | K78: =J78 -> 0.72173727 | L78: =K78 -> 0.72173727 | M78: =L78 -> 0.72173727 | N78: =M78 -> 0.72173727 | O78: =N78 -> 0.72173727
B81: 2022 | C81: 2023 | D81: 2024 | E81: 2025 | F81: 2026 E | G81: 2027 E | H81: 2028 E | I81: 2029 E | J81: 2030 E | K81: 2031 E | L81: 2032 E | M81: 2033 E | N81: 2034 E | O81: 2035 E
A82: Working Capital | B82: =B34-B61 -> 4787 | C82: =C34-C61 -> 7795.6 | D82: =D34-D61 -> 10307.7 | E82: =E73-E77 -> 5801.1 | F82: =F73-F77 -> 10690.3 | G82: =G73-G77 -> 12422.502 | H82: =H73-H77 -> 14050.381 | I82: =I73-I77 -> 15532.369 | J82: =J73-J77 -> 17167.073 | K82: =K73-K77 -> 18608.34 | L82: =L73-L77 -> 19878.44 | ... O82: =O73-O77 -> 23412.91
A83: Change in Working Capital | C83: =C82/B82-1 -> 0.62849384 | D83: =D82/C82-1 -> 0.32224588 | E83: =E82/D82-1 -> -0.43720714 | F83: =F82/E82-1 -> 0.84280564 | G83: =G82/F82-1 -> 0.16203499 | H83: =H82/G82-1 -> 0.1310427 | I83: =I82/H82-1 -> 0.10547678 | J83: =J82/I82-1 -> 0.10524496 | ... O83: =O82/N82-1 -> 0.050978793
A84: Working Capital Investment | C84: =C82-B82 -> 3008.6 | D84: =D82-C82 -> 2512.1 | E84: =E82-D82 -> -4506.6 | F84: =F82-E82 -> 4889.1998 | G84: =G82-F82 -> 1732.2026 | H84: =H82-G82 -> 1627.8782 | I84: =I82-H82 -> 1481.9889 | J84: =J82-I82 -> 1634.7037 | ... O84: =O82-N82 -> 1135.6669
B89: 2022 | C89: 2023 | D89: 2024 | E89: 2025 | F89: 2026 E | G89: 2027 E | H89: 2028 E | I89: 2029 E | J89: 2030 E | K89: 2031 E | L89: 2032 E | M89: 2033 E | N89: 2034 E | O89: 2035 E
A90: Property, plant and equipment, net | B90: 3944.2 | C90: 5493.2 | D90: 6846.8 | E90: 7893.8 | F90: ='ASML Revenue Model'!G7*F91 -> 8842.126 | G90: ='ASML Revenue Model'!H7*G91 -> 10274.86 | H90: ='ASML Revenue Model'!I7*H91 -> 11621.305 | I90: ='ASML Revenue Model'!J7*I91 -> 12847.083 | J90: ='ASML Revenue Model'!K7*J91 -> 14199.174 | K90: ='ASML Revenue Model'!L7*K91 -> 15391.27 | L90: ='ASML Revenue Model'!M7*L91 -> 16441.79 | M90: ='ASML Revenue Model'!N7*M91 -> 17447.538 | ... O90: ='ASML Revenue Model'!P7*O91 -> 19365.21
A91: PPE/revenue | B91: =B90/'ASML Revenue Model'!C7 -> 0.1862809 | C91: =C90/'ASML Revenue Model'!D7 -> 0.1993287 | D91: =D90/'ASML Revenue Model'!E7 -> 0.24225398 | E91: =E90/'ASML Revenue Model'!F7 -> 0.24164225 | F91: =AVERAGE(B91:E91) -> 0.21737646 | G91: =F91 -> 0.21737646 | H91: =G91 -> 0.21737646 | I91: =H91 -> 0.21737646 | J91: =I91 -> 0.21737646 | K91: =J91 -> 0.21737646 | L91: =K91 -> 0.21737646 | M91: =L91 -> 0.21737646 | N91: =M91 -> 0.21737646 | O91: =N91 -> 0.21737646
B94: 2022 | C94: 2023 | D94: 2024 | E94: 2025 | F94: 2026 E | G94: 2027 E | H94: 2028 E | I94: 2029 E | J94: 2030 E | K94: 2031 E | L94: 2032 E | M94: 2033 E | N94: 2034 E | O94: 2035 E
A95: Total non-current liabilities | B95: 9777.4 | C95: 10595.4 | D95: 10495.1 | E95: 6952.4 | F95: =F96*'ASML Revenue Model'!G7 -> 14546.036 | G95: =G96*'ASML Revenue Model'!H7 -> 16903.003 | H95: =H96*'ASML Revenue Model'!I7 -> 19118.018 | I95: =I96*'ASML Revenue Model'!J7 -> 21134.525 | J95: =J96*'ASML Revenue Model'!K7 -> 23358.827 | K95: =K96*'ASML Revenue Model'!L7 -> 25319.925 | L95: =L96*'ASML Revenue Model'!M7 -> 27048.119 | M95: =M96*'ASML Revenue Model'!N7 -> 28702.658 | ... O95: =O96*'ASML Revenue Model'!P7 -> 31857.388
A96: Total non-current liabilities/revenue | B96: =B95/'ASML Revenue Model'!C7 -> 0.46177751 | C96: =C95/'ASML Revenue Model'!D7 -> 0.3844694 | D96: =D95/'ASML Revenue Model'!E7 -> 0.3713384 | E96: =E95/'ASML Revenue Model'!F7 -> 0.21282445 | F96: =AVERAGE(B96:E96) -> 0.35760244 | G96: =F96 -> 0.35760244 | H96: =G96 -> 0.35760244 | I96: =H96 -> 0.35760244 | J96: =I96 -> 0.35760244 | K96: =J96 -> 0.35760244 | L96: =K96 -> 0.35760244 | M96: =L96 -> 0.35760244 | N96: =M96 -> 0.35760244 | O96: =N96 -> 0.35760244
B100: 2022 | C100: 2023 | D100: 2024 | E100: 2025 | F100: 2026 E | G100: 2027 E | H100: 2028 E | I100: 2029 E | J100: 2030 E | K100: 2031 E | L100: 2032 E | M100: 2033 E | N100: 2034 E | O100: 2035 E
A101: Total non-current assets | B101: 16276.4 | C101: 19009.3 | D101: 22209.3 | E101: 25336.3 | F101: =F102*'ASML Revenue Model'!G7 -> 30709.746 | G101: =G102*'ASML Revenue Model'!H7 -> 35685.799 | H101: =H102*'ASML Revenue Model'!I7 -> 40362.162 | I101: =I102*'ASML Revenue Model'!J7 -> 44619.433 | J101: =J102*'ASML Revenue Model'!K7 -> 49315.403 | K101: =K102*'ASML Revenue Model'!L7 -> 53455.694 | L101: =L102*'ASML Revenue Model'!M7 -> 57104.276 | M101: =M102*'ASML Revenue Model'!N7 -> 60597.354 | ... O101: =O102*'ASML Revenue Model'!P7 -> 67257.655
A102: Total non-current assets/revenue | B102: =B101/'ASML Revenue Model'!C7 -> 0.76871924 | C102: =C101/'ASML Revenue Model'!D7 -> 0.68977992 | D102: =D101/'ASML Revenue Model'!E7 -> 0.78581108 | E102: =E101/'ASML Revenue Model'!F7 -> 0.77558598 | F102: =AVERAGE(B102:E102) -> 0.75497406 | G102: =F102 -> 0.75497406 | H102: =G102 -> 0.75497406 | I102: =H102 -> 0.75497406 | J102: =I102 -> 0.75497406 | K102: =J102 -> 0.75497406 | L102: =K102 -> 0.75497406 | M102: =L102 -> 0.75497406 | N102: =M102 -> 0.75497406 | O102: =N102 -> 0.75497406
B108: 2022 | C108: 2023 | D108: 2024 | E108: 2025 | F108: 2026 E | G108: 2027 E | H108: 2028 E | I108: 2029 E | J108: 2030 E | K108: 2031 E | L108: 2032 E | M108: 2033 E | N108: 2034 E | O108: 2035 E
A109: Shareholders’ equity | B109: 11286 | C109: 16209.5 | D109: 22021.9 | E109: 24185 | F109: =F110*'ASML Revenue Model'!G7 -> 26854.009 | G109: =G110*'ASML Revenue Model'!H7 -> 31205.298 | H109: =H110*'ASML Revenue Model'!I7 -> 35294.525 | I109: =I110*'ASML Revenue Model'!J7 -> 39017.277 | J109: =J110*'ASML Revenue Model'!K7 -> 43123.649 | K109: =K110*'ASML Revenue Model'!L7 -> 46744.109 | L109: =L110*'ASML Revenue Model'!M7 -> 49934.596 | M109: =M110*'ASML Revenue Model'!N7 -> 52989.105 | ... O109: =O110*'ASML Revenue Model'!P7 -> 58813.177
A110: Shareholders’ equity/revenue | B110: =B109/'ASML Revenue Model'!C7 -> 0.53302729 | C110: =C109/'ASML Revenue Model'!D7 -> 0.58818513 | D110: =D109/'ASML Revenue Model'!E7 -> 0.77918048 | E110: =E109/'ASML Revenue Model'!F7 -> 0.74034279 | F110: =AVERAGE(B110:E110) -> 0.66018392 | G110: =F110 -> 0.66018392 | H110: =G110 -> 0.66018392 | I110: =H110 -> 0.66018392 | J110: =I110 -> 0.66018392 | K110: =J110 -> 0.66018392 | L110: =K110 -> 0.66018392 | M110: =L110 -> 0.66018392 | N110: =M110 -> 0.66018392 | O110: =N110 -> 0.66018392

Sheet Cash Flow
A1: IFRS
A2: Please note: The content of this file is qualified in its entirety by reference to the electronic version of the ASML 2025 Annual Report based on IFRS and therefore: (i) your local (browser and/or mobile device) settings can influence the way this table and its content is being displayed and (ii) (foot)notes have been deleted for reader's convenience.
A4: Always refer to the electronic version of the ASML 2025 Annual Report based on IFRS for the full and official financial information.
A6: Consolidated Statement of Cash Flows for the years ended December 31, 2022, 2023, 2024 and 2025
A8: Year ended December 31 (€, in millions) | B8: 2022 | C8: 2023 | D8: 2024 | E8: 2025
A10: Cash flows from operating activities
A11: Net income | B11: 6395.8 | C11: 8115.2 | D11: 8349 | E11: 10213
A12: Adjustments to reconcile net income to net cash flows from operating activities:
A13: Depreciation and amortization | B13: 875.9 | C13: 1047.5 | D13: 1200.1 | E13: 1432.8
A14: Impairment and loss on disposal | B14: 39.3 | C14: 37.5 | D14: 35.8 | E14: 49.7
A15: Share-based compensation expense | B15: 66.4 | C15: 139.8 | D15: 182.1 | E15: 215.4
A16: Gain on sale of subsidiaries | B16: 0 | C16: 0 | D16: 0 | E16: 0
A17: Inventory reserves | B17: 278.5 | C17: 485.3 | D17: 554.7 | E17: 469.4
A18: Deferred tax expense (benefit) | B18: -774.7 | C18: 233.2 | D18: -38.1 | E18: 302.1
A19: Investments in associates | B19: 15.3 | C19: 4.2 | D19: 4.4 | E19: 94.6
A20: Changes in assets and liabilities:
A21: Accounts receivable, net | B21: -2338 | C21: 959.9 | D21: -139.9 | E21: 1415.5
A22: Finance receivables, net | B22: 212.2 | C22: -88.6 | D22: 1038.7 | E22: -227.2
A23: Inventories | B23: -2080.9 | C23: -1646.9 | D23: -1860.9 | E23: -832.5
A24: Other assets | B24: -611.4 | C24: -532.6 | D24: -1246.9 | E24: -562.1
A25: Accrued and other liabilities | B25: 278.7 | C25: 539 | D25: 634 | E25: -230.5
A26: Accounts payable | B26: 405.3 | C26: -261.1 | D26: 1126.7 | E26: 15.2
A27: Current tax assets and liabilities | B27: 39.8 | C27: -931.6 | D27: 658.2 | E27: 348.7
A28: Contract assets and liabilities | B28: 6632.7 | C28: -1564.6 | D28: 1871.8 | E28: 1122.4
A29: Net cash provided by operating activities | B29: 9434.9 | C29: 6536.2 | D29: 12369.7 | E29: 13826.5
A31: Cash flows from investing activities
A32: Purchase of property, plant and equipment | B32: -1281.8 | C32: -2155.6 | D32: -2067.2 | E32: -1573.6
A33: Purchase of intangible assets | B33: -930.6 | C33: -985.9 | D33: -1138.4 | E33: -1136.8
A34: Purchase of short-term investments | B34: -334.3 | C34: -23.6 | D34: -305.2 | E34: -406.2
A35: Maturity of short-term investments | B35: 864.7 | C35: 125.6 | D35: 305.2 | E35: 5.3
A36: Purchase of equity investments | B36: 0 | C36: 0 | D36: 0 | E36: -1302.2
A37: Loans issued and other investments | B37: -240 | C37: -561.5 | D37: -526.2 | E37: -703.7
A38: Repayment on loans5 | B38: 0 | C38: 0 | D38: 0 | E38: 260.2
A39: Acquisition of subsidiaries (net of cash acquired) | C39: -33.6 | D39: 0 | E39: 0
A40: Net cash used in investing activities | B40: -1922 | C40: -3634.6 | D40: -3731.8 | E40: -4857
A42: Cash flows from financing activities
A43: Dividend paid | B43: -2559.8 | C43: -2348.3 | D43: -2452.9 | E43: -2550.3
A44: Purchase of treasury shares | B44: -4639.7 | C44: -1000 | D44: -500 | E44: -5950
A45: Net proceeds from issuance of shares | B45: 81.8 | C45: 99.4 | D45: 124 | E45: 142.3
A46: Net proceeds from issuance of borrowings | B46: 495.6 | C46: 997.8 | D46: 22.5 | E46: 754.1
A47: Repayment of debt and lease obligations | B47: -571.2 | C47: -900.3 | D47: -106.7 | E47: -1155.4
A48: Net cash used in financing activities | B48: -7193.3 | C48: -3151.4 | D48: -2913.1 | E48: -8759.3
A50: Net cash flows | B50: 319.6 | C50: -249.8 | D50: 5724.8 | E50: 210.2
A51: Effect of changes in exchange rates on cash | B51: -3.1 | C51: -13.8 | D51: 6.4 | E51: -30.1
A52: Net increase (decrease) in cash and cash equivalents | B52: 316.5 | C52: -263.6 | D52: 5731.2 | E52: 180.1
A53: Cash and cash equivalents at beginning of the year | B53: 6951.8 | C53: 7268.3 | D53: 7004.7 | E53: 12735.9
A54: Cash and cash equivalents at end of the year | B54: 7268.3 | C54: 7004.7 | D54: 12735.9 | E54: 12916
A56: Supplemental disclosures of cash flow information | B56: 50.3
A57: Change in unpaid portion of property, plant and equipment, excluded in investing activities, included in accounts payable | B57: 42.4 | C57: 49.3 | D57: 23.6 | E57: 22.3
A58: Interest received | B58: -82.2 | C58: 190.8 | D58: 169.5 | E58: 201.3
A59: Interest paid | B59: -1734.6 | C59: -137.8 | D59: -160 | E59: -114.5
A60: Income taxes paid, net of refunds | B60: -2568.3 | C60: -2568.3 | D60: -1098 | E60: -1621.4
A64: Calculation for Cash Flow Items Forecasting
B67: 2022 | C67: 2023 | D67: 2024 | E67: 2025 | F67: 2026 E | G67: 2027 E | H67: 2028 E | I67: 2029 E | J67: 2030 E | K67: 2031 E | L67: 2032 E | M67: 2033 E | N67: 2034 E | O67: 2035 E
A68: Dividend paid | B68: -2559.8 | C68: -2348.3 | D68: -2452.9 | E68: -2550.3 | F68: =-F70*'Pro Forma Financial Statement'!C27 -> -3432.0503 | G68: =-G70*'Pro Forma Financial Statement'!D27 -> -4024.9834 | H68: =-H70*'Pro Forma Financial Statement'!E27 -> -4592.6608 | I68: =-I70*'Pro Forma Financial Statement'!F27 -> -5120.4904 | J68: =-J70*'Pro Forma Financial Statement'!G27 -> -5707.0688 | K68: =-K70*'Pro Forma Financial Statement'!H27 -> -6237.0675 | L68: =-L70*'Pro Forma Financial Statement'!I27 -> -6716.5254 | M68: =-M70*'Pro Forma Financial Statement'!J27 -> -7184.1111 | ... O68: =-O70*'Pro Forma Financial Statement'!L27 -> -8098.9625
A69: Purchase of treasury shares | B69: -4639.7 | C69: -1000 | D69: -500 | E69: -5950 | F69: =-F71*'Pro Forma Financial Statement'!C19 -> -4150.1961 | G69: =-G71*'Pro Forma Financial Statement'!D19 -> -4867.1986 | H69: =-H71*'Pro Forma Financial Statement'!E19 -> -5553.6608 | I69: =-I71*'Pro Forma Financial Statement'!F19 -> -6191.9371 | J69: =-J71*'Pro Forma Financial Statement'!G19 -> -6901.2553 | K69: =-K71*'Pro Forma Financial Statement'!H19 -> -7542.1545 | L69: =-L71*'Pro Forma Financial Statement'!I19 -> -8121.9375 | M69: =-M71*'Pro Forma Financial Statement'!J19 -> -8687.364 | ... O69: =-O71*'Pro Forma Financial Statement'!L19 -> -9793.6452
A70: dividend payout ratio | B70: =-B68/B11 -> 0.4002314 | C70: =-C68/C11 -> 0.28937056 | D70: =-D68/D11 -> 0.29379566 | E70: =-E68/E11 -> 0.24971115 | F70: =AVERAGE(B70:E70) -> 0.3082772 | G70: =F70 -> 0.3082772 | H70: =G70 -> 0.3082772 | I70: =H70 -> 0.3082772 | J70: =I70 -> 0.3082772 | K70: =J70 -> 0.3082772 | L70: =K70 -> 0.3082772 | M70: =L70 -> 0.3082772 | N70: =M70 -> 0.3082772 | O70: =N70 -> 0.3082772
A71: share buyback ratio | B71: =-B69/B11 -> 0.72542919 | C71: =-C69/C11 -> 0.12322555 | D71: =-D69/D11 -> 0.059887412 | E71: =-E69/E11 -> 0.58259082 | F71: =AVERAGE(B71:E71) -> 0.37278324 | G71: =F71 -> 0.37278324 | H71: =G71 -> 0.37278324 | I71: =H71 -> 0.37278324 | J71: =I71 -> 0.37278324 | K71: =J71 -> 0.37278324 | L71: =K71 -> 0.37278324 | M71: =L71 -> 0.37278324 | N71: =M71 -> 0.37278324 | O71: =N71 -> 0.37278324
A73: Dividends Paid / Share Buybacks and Cancellation | B73: =SUM(B68:B69) -> -7199.5 | C73: =SUM(C68:C69) -> -3348.3 | D73: =SUM(D68:D69) -> -2952.9 | E73: =SUM(E68:E69) -> -8500.3 | F73: =F68+F69 -> -7582.2464 | G73: =G68+G69 -> -8892.182 | H73: =H68+H69 -> -10146.322 | I73: =I68+I69 -> -11312.428 | J73: =J68+J69 -> -12608.324 | K73: =K68+K69 -> -13779.222 | L73: =L68+L69 -> -14838.463 | M73: =M68+M69 -> -15871.475 | ... O73: =O68+O69 -> -17892.608
A74: pay out ratio to net income | B74: =-B73/B11 -> 1.1256606 | C74: =-C73/C11 -> 0.41259612 | D74: =-D73/D11 -> 0.35368308 | E74: =-E73/E11 -> 0.83230197 | F74: =-F73/'Pro Forma Financial Statement'!C19 -> 0.68106044 | G74: =-G73/'Pro Forma Financial Statement'!D19 -> 0.68106044 | H74: =-H73/'Pro Forma Financial Statement'!E19 -> 0.68106044 | I74: =-I73/'Pro Forma Financial Statement'!F19 -> 0.68106044 | J74: =-J73/'Pro Forma Financial Statement'!G19 -> 0.68106044 | K74: =-K73/'Pro Forma Financial Statement'!H19 -> 0.68106044 | L74: =-L73/'Pro Forma Financial Statement'!I19 -> 0.68106044 | M74: =-M73/'Pro Forma Financial Statement'!J19 -> 0.68106044 | ... O74: =-O73/'Pro Forma Financial Statement'!L19 -> 0.68106044
B78: 2022 | C78: 2023 | D78: 2024 | E78: 2025 | F78: 2026 E | G78: 2027 E | H78: 2028 E | I78: 2029 E | J78: 2030 E | K78: 2031 E | L78: 2032 E | M78: 2033 E | N78: 2034 E | O78: 2035 E
A79: Purchase of property, plant and equipment (CAPEX) | B79: =B32*-1 -> 1281.8 | C79: =C32*-1 -> 2155.6 | D79: =D32*-1 -> 2067.2 | E79: =E32*-1 -> 1573.6 | F79: =F80*'ASML Revenue Model'!G7 -> 2644.684 | G79: =G80*'ASML Revenue Model'!H7 -> 3073.2153 | H79: =H80*'ASML Revenue Model'!I7 -> 3475.9378 | I79: =I80*'ASML Revenue Model'!J7 -> 3842.5685 | J79: =J80*'ASML Revenue Model'!K7 -> 4246.9795 | K79: =K80*'ASML Revenue Model'!L7 -> 4603.536 | L79: =L80*'ASML Revenue Model'!M7 -> 4917.7472 | M79: =M80*'ASML Revenue Model'!N7 -> 5218.5667 | ... O79: =O80*'ASML Revenue Model'!P7 -> 5792.1433
A80: capex ratio to revenue | B80: =B79/'ASML Revenue Model'!C7 -> 0.060538222 | C80: =C79/'ASML Revenue Model'!D7 -> 0.078219061 | D80: =D79/'ASML Revenue Model'!E7 -> 0.073141822 | E80: =E79/'ASML Revenue Model'!F7 -> 0.048170495 | F80: =AVERAGE(B80:E80) -> 0.0650174 | G80: =F80 -> 0.0650174 | H80: =G80 -> 0.0650174 | I80: =H80 -> 0.0650174 | J80: =I80 -> 0.0650174 | K80: =J80 -> 0.0650174 | L80: =K80 -> 0.0650174 | M80: =L80 -> 0.0650174 | N80: =M80 -> 0.0650174 | O80: =N80 -> 0.0650174

Sheet Statement of Profit or Loss
A1: IFRS
A2: Please note: The content of this file is qualified in its entirety by reference to the electronic version of the ASML 2025 Annual Report based on IFRS and therefore: (i) your local (browser and/or mobile device) settings can influence the way this table and its content is being displayed and (ii) (foot)notes have been deleted for reader's convenience.
A4: Always refer to the electronic version of the ASML 2025 Annual Report based on IFRS for the full and official financial information.
A6: Consolidated Statement of Profit or Loss for the years ended December 31, 2022, 2023, 2024 and 2025
A8: Year ended December 31 (€, in millions, except per share data) | B8: 2022 | C8: 2023 | D8: 2024 | E8: 2025
A9: Net system sales | B9: 15430.3 | C9: 21938.6 | D9: 21768.7 | E9: 24474.3
A10: Net service and field option sales | B10: 5743.1 | C10: 5619.9 | D10: 6494.2 | E10: 8193
A11: Total net sales | B11: 21173.4 | C11: 27558.5 | D11: 28262.9 | E11: 32667.3
A13: Cost of system sales | B13: -7843.3 | C13: -10439.1 | D13: -10615.1 | E13: -11710.6
A14: Cost of service and field option sales | B14: -2817.4 | C14: -3345 | D14: -3364 | E14: -4025.3
A15: Total cost of sales | B15: -10660.7 | C15: -13784.1 | D15: -13979.1 | E15: -15735.9
A17: Gross profit | B17: 10512.7 | C17: 13774.4 | D17: 14283.8 | E17: 16931.4
A19: Research and development costs | B19: -2282.1 | C19: -3113.1 | D19: -3181 | E19: -3619.6
A20: Selling, general and administrative costs | B20: -909.6 | C20: -1149.4 | D20: -1165.7 | E20: -1257.8
A21: Other income | B21: 0 | C21: 0 | D21: 0 | E21: 0
A22: Operating income | B22: 7321 | C22: 9511.9 | D22: 9937.1 | E22: 12054 | F22: =E22*(1-'DCF Model'!O4) -> 8944.068
A24: Finance income | B24: 16.2 | C24: 193.9 | D24: 182.4 | E24: 223
A25: Finance costs | B25: -60.8 | C25: -152.7 | D25: -162.6 | E25: -118.3
A26: Income before income taxes | B26: 7276.4 | C26: 9553.1 | D26: 9956.9 | E26: 12158.7
A28: Income tax expense | B28: -1018.6 | C28: -1629.2 | D28: -1817.7 | E28: -2162.4
A29: Income after income taxes | B29: 6257.8 | C29: 7923.9 | D29: 8139.2 | E29: 9996.3
A31: Profit from investments in associates | B31: 138 | C31: 191.3 | D31: 209.8 | E31: 216.7
A32: Net income | B32: 6395.8 | C32: 8115.2 | D32: 8349 | E32: 10213
A34: Basic net income per ordinary share | B34: 16.08 | C34: 20.61 | D34: 21.23 | E34: 26.29
A35: Diluted net income per ordinary share | B35: 16.07 | C35: 20.59 | D35: 21.21 | E35: 26.26
A36: Number of ordinary shares used in computing per share amounts
A37: Basic | B37: 397.7 | C37: 393.8 | D37: 393.3 | E37: 388.5
A38: Diluted | B38: 398 | C38: 394.1 | D38: 393.6 | E38: 388.9
A40: Net Profit Margin | B40: =B32/B11 -> 0.30206769 | C40: =C32/C11 -> 0.29447176 | D40: =D32/D11 -> 0.29540493 | E40: =E32/E11 -> 0.3126368

Sheet Changes in Equity
A1: IFRS
A2: Please note: The content of this file is qualified in its entirety by reference to the electronic version of the ASML 2025 Annual Report based on IFRS and therefore: (i) your local (browser and/or mobile device) settings can influence the way this table and its content is being displayed and (ii) (foot)notes have been deleted for reader's convenience.
A4: Always refer to the electronic version of the ASML 2025 Annual Report based on IFRS for the full and official financial information.
A6: Consolidated Statement of Changes in Equity for the years ended December 31, 2022, 2023, 2024 and 2025
B8: Issued and Outstanding Shares
A9: (€, in millions) | B9: Number | C9: Share Capital | D9: Share Premium | E9: Treasury Shares at Cost | F9: Retained Earnings | G9: Other Reserves | H9: Net Income | I9: Total
A10: Balance at January 1, 2022 | B10: 402.6 | C10: 36.5 | D10: 4369.4 | E10: -2422.8 | F10: 1663 | G10: 2063.1 | H10: 6134.6 | I10: 11843.8
A11: Prior year net income | B11: 0 | C11: 0 | D11: 0 | E11: 0 | F11: 6134.6 | G11: 0 | H11: -6134.6 | I11: 0
A13: Components of comprehensive income:
A14: Net income | B14: 0 | C14: 0 | D14: 0 | E14: 0 | F14: 0 | G14: 0 | H14: 6395.8 | I14: 6395.8
A15: Proportionate share of other comprehensive income from associates | B15: 0 | C15: 0 | D15: 0 | E15: 0 | F15: 0 | G15: 37.7 | H15: 0 | I15: 37.7
A16: Gain (loss) on foreign currency translation | B16: 0 | C16: 0 | D16: 0 | E16: 0 | F16: 0 | G16: 68.9 | H16: 0 | I16: 68.9
A17: Gain (loss) on financial instruments | B17: 0 | C17: 0 | D17: 0 | E17: 0 | F17: 0 | G17: -8.9 | H17: 0 | I17: -8.9
A18: Total comprehensive income | B18: 0 | C18: 0 | D18: 0 | E18: 0 | F18: 0 | G18: 97.7 | H18: 6395.8 | I18: 6493.5
A20: Purchase of treasury shares | B20: -8.5 | C20: 0 | D20: 0 | E20: -4639.7 | F20: 0 | G20: 0 | H20: 0 | I20: -4639.7
A21: Cancellation of treasury shares | B21: 0 | C21: -0.3 | D21: 0 | E21: 2333.7 | F21: -2333.4 | G21: 0 | H21: 0 | I21: 0
A22: Share-based payments | B22: 0 | C22: 0 | D22: 66.4 | E22: 0 | F22: 0 | G22: 0 | H22: 0 | I22: 66.4
A23: Issuance of shares | B23: 0.5 | C23: 0.1 | D23: -4.2 | E23: 87.5 | F23: -1.6 | G23: 0 | H23: 0 | I23: 81.8
A24: Dividend paid | B24: 0 | C24: 0 | D24: 0 | E24: 0 | F24: -2559.8 | G24: 0 | H24: 0 | I24: -2559.8
A25: Development expenditures | B25: 0 | C25: 0 | D25: 0 | E25: 0 | F25: -600.9 | G25: 600.9 | H25: 0 | I25: 0
A26: Balance at December 31, 2022 | B26: 394.6 | C26: 36.3 | D26: 4431.6 | E26: -4641.3 | F26: 2301.9 | G26: 2761.7 | H26: 6395.8 | I26: 11286
A27: Prior year net income | B27: 0 | C27: 0 | D27: 0 | E27: 0 | F27: 6395.8 | G27: 0 | H27: -6395.8 | I27: 0
A29: Components of comprehensive income:
A30: Net income | B30: 0 | C30: 0 | D30: 0 | E30: 0 | F30: 0 | G30: 0 | H30: 8115.2 | I30: 8115.2
A31: Proportionate share of other comprehensive income from associates | B31: 0 | C31: 0 | D31: 0 | E31: 0 | F31: 0 | G31: 0.2 | H31: 0 | I31: 0.2
A32: Gain (loss) on foreign currency translation | B32: 0 | C32: 0 | D32: 0 | E32: 0 | F32: 0 | G32: -67.6 | H32: 0 | I32: -67.6
A33: Gain (loss) on financial instruments | B33: 0 | C33: 0 | D33: 0 | E33: 0 | F33: 0 | G33: -15.2 | H33: 0 | I33: -15.2
A34: Total comprehensive income | B34: 0 | C34: 0 | D34: 0 | E34: 0 | F34: 0 | G34: -82.6 | H34: 8115.2 | I34: 8032.6
A36: Purchase of treasury shares | B36: -1.6 | C36: 0 | D36: 0 | E36: -1000 | F36: 0 | G36: 0 | H36: 0 | I36: -1000
A37: Cancellation of treasury shares | B37: 0 | C37: -0.3 | D37: 0 | E37: 2105.1 | F37: -2104.8 | G37: 0 | H37: 0 | I37: 0
A38: Share-based payments | B38: 0 | C38: 0 | D38: 139.8 | E38: 0 | F38: 0 | G38: 0 | H38: 0 | I38: 139.8
A39: Issuance of shares | B39: 0.5 | C39: 0 | D39: -77.5 | E39: 230 | F39: -53.1 | G39: 0 | H39: 0 | I39: 99.4
A40: Dividend paid | B40: 0 | C40: 0 | D40: 0 | E40: 0 | F40: -2348.3 | G40: 0 | H40: 0 | I40: -2348.3
A41: Development expenditures | B41: 0 | C41: 0 | D41: 0 | E41: 0 | F41: -689.1 | G41: 689.1 | H41: 0 | I41: 0
A42: Balance at January 1, 2023 | B42: 394.6 | C42: 36.3 | D42: 4431.6 | E42: -4641.3 | F42: 2301.9 | G42: 2761.7 | H42: 6395.8 | I42: 11286
A43: Prior year net income | B43: 0 | C43: 0 | D43: 0 | E43: 0 | F43: 6395.8 | G43: 0 | H43: -6395.8 | I43: 0
A45: Components of comprehensive income:
A46: Net income | B46: 0 | C46: 0 | D46: 0 | E46: 0 | F46: 0 | G46: 0 | H46: 8115.2 | I46: 8115.2
A47: Proportionate share of other comprehensive income from associates | B47: 0 | C47: 0 | D47: 0 | E47: 0 | F47: 0 | G47: 0.2 | H47: 0 | I47: 0.2
A48: Gain (loss) on equity investments | B48: 0 | C48: 0 | D48: 0 | E48: 0 | F48: 0 | G48: 0 | H48: 0 | I48: 0
A49: Gain (loss) on foreign currency translation | B49: 0 | C49: 0 | D49: 0 | E49: 0 | F49: 0 | G49: -67.6 | H49: 0 | I49: -67.6
A50: Gain (loss) on financial instruments | B50: 0 | C50: 0 | D50: 0 | E50: 0 | F50: 0 | G50: -15.2 | H50: 0 | I50: -15.2
A51: Total comprehensive income | B51: 0 | C51: 0 | D51: 0 | E51: 0 | F51: 0 | G51: -82.6 | H51: 8115.2 | I51: 8032.6
A53: Purchase of treasury shares | B53: -1.6 | C53: 0 | D53: 0 | E53: -1000 | F53: 0 | G53: 0 | H53: 0 | I53: -1000
A54: Cancellation of treasury shares | B54: 0 | C54: -0.3 | D54: 0 | E54: 2105.1 | F54: -2104.8 | G54: 0 | H54: 0 | I54: 0
A55: Share-based payments | B55: 0 | C55: 0 | D55: 139.8 | E55: 0 | F55: 0 | G55: 0 | H55: 0 | I55: 139.8
A56: Issuance of shares | B56: 0.5 | C56: 0 | D56: -77.5 | E56: 230 | F56: -53.1 | G56: 0 | H56: 0 | I56: 99.4
A57: Dividend paid | B57: 0 | C57: 0 | D57: 0 | E57: 0 | F57: -2348.3 | G57: 0 | H57: 0 | I57: -2348.3
A58: Development expenditures | B58: 0 | C58: 0 | D58: 0 | E58: 0 | F58: -689.1 | G58: 689.1 | H58: 0 | I58: 0
... A60: Prior year net income | B60: 0 | C60: 0 | D60: 0 | E60: 0 | F60: 8115.2 | G60: 0 | H60: -8115.2 | I60: 0
A62: Components of comprehensive income:
A63: Net income | B63: 0 | C63: 0 | D63: 0 | E63: 0 | F63: 0 | G63: 0 | H63: 8349 | I63: 8349
A64: Proportionate share of other comprehensive income from associates | B64: 0 | C64: 0 | D64: 0 | E64: 0 | F64: 0 | G64: -12.1 | H64: 0 | I64: -12.1
A65: Gain (loss) on equity investments | B65: 0 | C65: 0 | D65: 0 | E65: 0 | F65: 0 | G65: 0 | H65: 0 | I65: 0
A66: Gain (loss) on foreign currency translation | B66: 0 | C66: 0 | D66: 0 | E66: 0 | F66: 0 | G66: 93 | H66: 0 | I66: 93
A67: Gain (loss) on financial instruments | B67: 0 | C67: 0 | D67: 0 | E67: 0 | F67: 0 | G67: 29.3 | H67: 0 | I67: 29.3
A68: Total comprehensive income | B68: 0 | C68: 0 | D68: 0 | E68: 0 | F68: 0 | G68: 110.2 | H68: 8349 | I68: 8459.2
A70: Purchase of treasury shares | B70: -0.6 | C70: -0.1 | D70: 0 | E70: -499.9 | F70: 0 | G70: 0 | H70: 0 | I70: -500
A71: Cancellation of treasury shares | B71: 0 | C71: -0.5 | D71: 0 | E71: 3050.4 | F71: -3049.9 | G71: 0 | H71: 0 | I71: 0
A72: Share-based payments | B72: 0 | C72: 0 | D72: 182.1 | E72: 0 | F72: 0 | G72: 0 | H72: 0 | I72: 182.1
A73: Issuance of shares | B73: 0.4 | C73: 0 | D73: -121.7 | E73: 279.7 | F73: -34 | G73: 0 | H73: 0 | I73: 124
A74: Dividend paid | B74: 0 | C74: 0 | D74: 0 | E74: 0 | F74: -2452.9 | G74: 0 | H74: 0 | I74: -2452.9
A75: Development expenditures | B75: 0 | C75: 0 | D75: 0 | E75: 0 | F75: -914.6 | G75: 914.6 | H75: 0 | I75: 0
... A77: Prior year net income | B77: 0 | C77: 0 | D77: 0 | E77: 0 | F77: 8349 | G77: 0 | H77: -8349 | I77: 0
A79: Components of comprehensive income:
A80: Net income | B80: 0 | C80: 0 | D80: 0 | E80: 0 | F80: 0 | G80: 0 | H80: 10213 | I80: 10213
A81: Proportionate share of other comprehensive income from associates | B81: 0 | C81: 0 | D81: 0 | E81: 0 | F81: 0 | G81: 14.1 | H81: 0 | I81: 14.1
A82: Gain (loss) on equity investments | B82: 0 | C82: 0 | D82: 0 | E82: 0 | F82: 0 | G82: 416 | H82: 0 | I82: 416
A83: Gain (loss) on foreign currency translation | B83: 0 | C83: 0 | D83: 0 | E83: 0 | F83: 0 | G83: -262.8 | H83: 0 | I83: -262.8
A84: Gain (loss) on financial instruments | B84: 0 | C84: 0 | D84: 0 | E84: 0 | F84: 0 | G84: -74.6 | H84: 0 | I84: -74.6
A85: Total comprehensive income | B85: 0 | C85: 0 | D85: 0 | E85: 0 | F85: 0 | G85: 92.7 | H85: 10213 | I85: 10305.7
A87: Purchase of treasury shares | B87: -8.3 | C87: 0 | D87: 0 | E87: -5950 | F87: 0 | G87: 0 | H87: 0 | I87: -5950
A88: Cancellation of treasury shares | B88: 0 | C88: -0.5 | D88: 0 | E88: 3778.3 | F88: -3777.8 | G88: 0 | H88: 0 | I88: 0
A89: Share-based payments | B89: 0 | C89: 0 | D89: 215.4 | E89: 0 | F89: 0 | G89: 0 | H89: 0 | I89: 215.4
A90: Issuance of shares | B90: 0.4 | C90: 0 | D90: -144.2 | E90: 394.8 | F90: -108.3 | G90: 0 | H90: 0 | I90: 142.3
A91: Dividend paid | B91: 0 | C91: 0 | D91: 0 | E91: 0 | F91: -2550.3 | G91: 0 | H91: 0 | I91: -2550.3
A92: Development expenditures | B92: 0 | C92: 0 | D92: 0 | E92: 0 | F92: -757.4 | G92: 757.4 | H92: 0 | I92: 0
A93: Balance at December 31, 2025 | B93: 385.4 | C93: 34.9 | D93: 4625.5 | E93: -2252.9 | F93: 6321.8 | G93: 5242.7 | H93: 10213 | I93: 24185

Sheet Comprehensive Income
A1: IFRS
A2: Please note: The content of this file is qualified in its entirety by reference to the electronic version of the ASML 2025 Annual Report based on IFRS and therefore: (i) your local (browser and/or mobile device) settings can influence the way this table and its content is being displayed and (ii) (foot)notes have been deleted for reader's convenience.
A4: Always refer to the electronic version of the ASML 2025 Annual Report based on IFRS for the full and official financial information.
A6: Consolidated Statement of Comprehensive Income for the years ended December 31, 2022, 2023, 2024 and 2025
A8: Year ended December 31 (€, in millions) | B8: 2022 | C8: 2023 | D8: 2024 | E8: 2025
A9: Net income | B9: 6395.8 | C9: 8115.2 | D9: 8349 | E9: 10213
A11: Other comprehensive income:
A12: Proportionate share of other comprehensive income from associates | B12: 37.7 | C12: 0.2 | D12: -12.1 | E12: 14.1
A14: Foreign currency translation, net of taxes:
A15: Gain (loss) on foreign currency translation | B15: 68.9 | C15: -67.6 | D15: 93 | E15: -262.8
A17: Financial instruments, net of taxes:
A18: Gain (loss) on equity investments | B18: 0 | C18: 0 | D18: 0 | E18: 416
A19: Gain (loss) on derivative financial instruments | B19: 57.6 | C19: -15.8 | D19: 38.2 | E19: -88.4
A20: Transfers to net income from derivative financial instruments | B20: -66.5 | C20: 0.6 | D20: -8.9 | E20: 13.8
A21: Other comprehensive income, net of taxes | B21: 97.7 | C21: -82.6 | D21: 110.2 | E21: 92.7
A23: Total comprehensive income, net of taxes | B23: 6493.5 | C23: 8032.6 | D23: 8459.2 | E23: 10305.7
A24: Attributable to equity holders | B24: 6493.5 | C24: 8032.6 | D24: 8459.2 | E24: 10305.7
